{
  "values": [
    {
      "raidEnemyInfo": {
        "romVer": "BOTH",
        "no": 14001,
        "deliveryGroupID": 0,
        "difficulty": 0,
        "rate": 100,
        "dropTableFix": 6567696299599659786,
        "dropTableRandom": 6567696299599659786,
        "captureRate": 1,
        "captureLv": 45,
        "bossPokePara": {
          "devId": "DEV_PIKUSII",
          "formId": 0,
          "sex": "DEFAULT",
          "item": "ITEMID_NONE",
          "level": 45,
          "ballId": "NONE",
          "wazaType": "MANUAL",
          "waza1": {
            "wazaId": "WAZA_MAZIKARUSYAIN",
            "pointUp": 0
          },
          "waza2": {
            "wazaId": "WAZA_SAIKOKINESISU",
            "pointUp": 0
          },
          "waza3": {
            "wazaId": "WAZA_MISUTOFIIRUDO",
            "pointUp": 0
          },
          "waza4": {
            "wazaId": "WAZA_KOMETTOPANTI",
            "pointUp": 0
          },
          "gemType": "RANDOM",
          "seikaku": "DEFAULT",
          "tokusei": "RANDOM_123",
          "talentType": "V_NUM",
          "talentValue": {
            "hp": 0,
            "atk": 0,
            "def": 0,
            "spAtk": 0,
            "spDef": 0,
            "agi": 0
          },
          "talentVnum": 3,
          "effortValue": {
            "hp": 0,
            "atk": 0,
            "def": 0,
            "spAtk": 0,
            "spDef": 0,
            "agi": 0
          },
          "rareType": "DEFAULT",
          "scaleType": "RANDOM",
          "scaleValue": 0
        },
        "bossPokeSize": {
          "heightType": "RANDOM",
          "heigntValue": 0,
          "weightType": "RANDOM",
          "waightValue": 0,
          "scaleType": "RANDOM",
          "scaleValue": 0
        },
        "bossDesc": {
          "hpCoef": 1200,
          "powerChargeTrigerHp": 50,
          "powerChargeTrigerTime": 40,
          "powerChargeLimitTime": 9999,
          "powerChargeCancelDamage": 20,
          "powerChargePenaltyTime": 0,
          "powerChargePenaltyAction": "WAZA_KAMINARI",
          "powerChargeDamageRate": 20,
          "powerChargeGemDamageRate": 80,
          "powerChargeChangeGemDamageRate": 40,
          "extraAction1": {
            "timming": "HP",
            "action": "WAZA",
            "value": 90,
            "wazano": "WAZA_MEISOU"
          },
          "extraAction2": {
            "timming": "TIME",
            "action": "BOSS_STATUS_RESET",
            "value": 70,
            "wazano": "WAZA_NULL"
          },
          "extraAction3": {
            "timming": "NONE",
            "action": "NONE",
            "value": 0,
            "wazano": "WAZA_NULL"
          },
          "extraAction4": {
            "timming": "NONE",
            "action": "NONE",
            "value": 0,
            "wazano": "WAZA_NULL"
          },
          "extraAction5": {
            "timming": "NONE",
            "action": "NONE",
            "value": 0,
            "wazano": "WAZA_NULL"
          },
          "extraAction6": {
            "timming": "NONE",
            "action": "NONE",
            "value": 0,
            "wazano": "WAZA_NULL"
          },
          "doubleActionTrigerHp": 0,
          "doubleActionTrigerTime": 0,
          "doubleActionRate": 0
        },
        "raidTimeData": {
          "isActive": false,
          "gameLimit": 0,
          "clientLimit": 0,
          "commandLimit": 0,
          "pokeReviveTime": 0,
          "aiIntervalTime": 0,
          "aiIntervalRand": 0
        }
      }
    },
    {
      "raidEnemyInfo": {
        "romVer": "BOTH",
        "no": 14002,
        "deliveryGroupID": 0,
        "difficulty": 0,
        "rate": 100,
        "dropTableFix": 6567690802041518731,
        "dropTableRandom": 6567690802041518731,
        "captureRate": 1,
        "captureLv": 45,
        "bossPokePara": {
          "devId": "DEV_GOROON",
          "formId": 0,
          "sex": "DEFAULT",
          "item": "ITEMID_NONE",
          "level": 45,
          "ballId": "NONE",
          "wazaType": "MANUAL",
          "waza1": {
            "wazaId": "WAZA_ZIDANDA",
            "pointUp": 0
          },
          "waza2": {
            "wazaId": "WAZA_IWANADARE",
            "pointUp": 0
          },
          "waza3": {
            "wazaId": "WAZA_GANSEKIHUUZI",
            "pointUp": 0
          },
          "waza4": {
            "wazaId": "WAZA_TOSSIN",
            "pointUp": 0
          },
          "gemType": "RANDOM",
          "seikaku": "DEFAULT",
          "tokusei": "RANDOM_123",
          "talentType": "V_NUM",
          "talentValue": {
            "hp": 0,
            "atk": 0,
            "def": 0,
            "spAtk": 0,
            "spDef": 0,
            "agi": 0
          },
          "talentVnum": 3,
          "effortValue": {
            "hp": 0,
            "atk": 0,
            "def": 0,
            "spAtk": 0,
            "spDef": 0,
            "agi": 0
          },
          "rareType": "DEFAULT",
          "scaleType": "RANDOM",
          "scaleValue": 0
        },
        "bossPokeSize": {
          "heightType": "RANDOM",
          "heigntValue": 0,
          "weightType": "RANDOM",
          "waightValue": 0,
          "scaleType": "RANDOM",
          "scaleValue": 0
        },
        "bossDesc": {
          "hpCoef": 1200,
          "powerChargeTrigerHp": 50,
          "powerChargeTrigerTime": 40,
          "powerChargeLimitTime": 9999,
          "powerChargeCancelDamage": 20,
          "powerChargePenaltyTime": 0,
          "powerChargePenaltyAction": "WAZA_KAMINARI",
          "powerChargeDamageRate": 20,
          "powerChargeGemDamageRate": 80,
          "powerChargeChangeGemDamageRate": 40,
          "extraAction1": {
            "timming": "HP",
            "action": "WAZA",
            "value": 75,
            "wazano": "WAZA_IWANADARE"
          },
          "extraAction2": {
            "timming": "TIME",
            "action": "BOSS_STATUS_RESET",
            "value": 60,
            "wazano": "WAZA_NULL"
          },
          "extraAction3": {
            "timming": "NONE",
            "action": "NONE",
            "value": 0,
            "wazano": "WAZA_NULL"
          },
          "extraAction4": {
            "timming": "NONE",
            "action": "NONE",
            "value": 0,
            "wazano": "WAZA_NULL"
          },
          "extraAction5": {
            "timming": "NONE",
            "action": "NONE",
            "value": 0,
            "wazano": "WAZA_NULL"
          },
          "extraAction6": {
            "timming": "NONE",
            "action": "NONE",
            "value": 0,
            "wazano": "WAZA_NULL"
          },
          "doubleActionTrigerHp": 0,
          "doubleActionTrigerTime": 0,
          "doubleActionRate": 0
        },
        "raidTimeData": {
          "isActive": false,
          "gameLimit": 0,
          "clientLimit": 0,
          "commandLimit": 0,
          "pokeReviveTime": 0,
          "aiIntervalTime": 0,
          "aiIntervalRand": 0
        }
      }
    },
    {
      "raidEnemyInfo": {
        "romVer": "BOTH",
        "no": 14003,
        "deliveryGroupID": 0,
        "difficulty": 0,
        "rate": 100,
        "dropTableFix": 6567695200088031575,
        "dropTableRandom": 6567695200088031575,
        "captureRate": 1,
        "captureLv": 45,
        "bossPokePara": {
          "devId": "DEV_OOTATI",
          "formId": 0,
          "sex": "DEFAULT",
          "item": "ITEMID_NONE",
          "level": 45,
          "ballId": "NONE",
          "wazaType": "MANUAL",
          "waza1": {
            "wazaId": "WAZA_TOSSIN",
            "pointUp": 0
          },
          "waza2": {
            "wazaId": "WAZA_KAENHOUSYA",
            "pointUp": 0
          },
          "waza3": {
            "wazaId": "WAZA_HUIUTI",
            "pointUp": 0
          },
          "waza4": {
            "wazaId": "WAZA_AMAERU",
            "pointUp": 0
          },
          "gemType": "RANDOM",
          "seikaku": "DEFAULT",
          "tokusei": "RANDOM_123",
          "talentType": "V_NUM",
          "talentValue": {
            "hp": 0,
            "atk": 0,
            "def": 0,
            "spAtk": 0,
            "spDef": 0,
            "agi": 0
          },
          "talentVnum": 3,
          "effortValue": {
            "hp": 0,
            "atk": 0,
            "def": 0,
            "spAtk": 0,
            "spDef": 0,
            "agi": 0
          },
          "rareType": "DEFAULT",
          "scaleType": "RANDOM",
          "scaleValue": 0
        },
        "bossPokeSize": {
          "heightType": "RANDOM",
          "heigntValue": 0,
          "weightType": "RANDOM",
          "waightValue": 0,
          "scaleType": "RANDOM",
          "scaleValue": 0
        },
        "bossDesc": {
          "hpCoef": 1200,
          "powerChargeTrigerHp": 50,
          "powerChargeTrigerTime": 40,
          "powerChargeLimitTime": 9999,
          "powerChargeCancelDamage": 20,
          "powerChargePenaltyTime": 0,
          "powerChargePenaltyAction": "WAZA_KAMINARI",
          "powerChargeDamageRate": 20,
          "powerChargeGemDamageRate": 80,
          "powerChargeChangeGemDamageRate": 40,
          "extraAction1": {
            "timming": "HP",
            "action": "WAZA",
            "value": 90,
            "wazano": "WAZA_AMAERU"
          },
          "extraAction2": {
            "timming": "HP",
            "action": "PLAYER_STATUS_RESET",
            "value": 60,
            "wazano": "WAZA_NULL"
          },
          "extraAction3": {
            "timming": "NONE",
            "action": "NONE",
            "value": 0,
            "wazano": "WAZA_NULL"
          },
          "extraAction4": {
            "timming": "NONE",
            "action": "NONE",
            "value": 0,
            "wazano": "WAZA_NULL"
          },
          "extraAction5": {
            "timming": "NONE",
            "action": "NONE",
            "value": 0,
            "wazano": "WAZA_NULL"
          },
          "extraAction6": {
            "timming": "NONE",
            "action": "NONE",
            "value": 0,
            "wazano": "WAZA_NULL"
          },
          "doubleActionTrigerHp": 0,
          "doubleActionTrigerTime": 0,
          "doubleActionRate": 0
        },
        "raidTimeData": {
          "isActive": false,
          "gameLimit": 0,
          "clientLimit": 0,
          "commandLimit": 0,
          "pokeReviveTime": 0,
          "aiIntervalTime": 0,
          "aiIntervalRand": 0
        }
      }
    },
    {
      "raidEnemyInfo": {
        "romVer": "BOTH",
        "no": 14004,
        "deliveryGroupID": 0,
        "difficulty": 0,
        "rate": 100,
        "dropTableFix": 6567696299599659786,
        "dropTableRandom": 6567696299599659786,
        "captureRate": 1,
        "captureLv": 45,
        "bossPokePara": {
          "devId": "DEV_YORUNOZUKU",
          "formId": 0,
          "sex": "DEFAULT",
          "item": "ITEMID_NONE",
          "level": 45,
          "ballId": "NONE",
          "wazaType": "MANUAL",
          "waza1": {
            "wazaId": "WAZA_EASURASSYU",
            "pointUp": 0
          },
          "waza2": {
            "wazaId": "WAZA_ZINTUURIKI",
            "pointUp": 0
          },
          "waza3": {
            "wazaId": "WAZA_MUUNFOOSU",
            "pointUp": 0
          },
          "waza4": {
            "wazaId": "WAZA_RIHUREKUTAA",
            "pointUp": 0
          },
          "gemType": "RANDOM",
          "seikaku": "DEFAULT",
          "tokusei": "RANDOM_123",
          "talentType": "V_NUM",
          "talentValue": {
            "hp": 0,
            "atk": 0,
            "def": 0,
            "spAtk": 0,
            "spDef": 0,
            "agi": 0
          },
          "talentVnum": 3,
          "effortValue": {
            "hp": 0,
            "atk": 0,
            "def": 0,
            "spAtk": 0,
            "spDef": 0,
            "agi": 0
          },
          "rareType": "DEFAULT",
          "scaleType": "RANDOM",
          "scaleValue": 0
        },
        "bossPokeSize": {
          "heightType": "RANDOM",
          "heigntValue": 0,
          "weightType": "RANDOM",
          "waightValue": 0,
          "scaleType": "RANDOM",
          "scaleValue": 0
        },
        "bossDesc": {
          "hpCoef": 1200,
          "powerChargeTrigerHp": 50,
          "powerChargeTrigerTime": 40,
          "powerChargeLimitTime": 9999,
          "powerChargeCancelDamage": 20,
          "powerChargePenaltyTime": 0,
          "powerChargePenaltyAction": "WAZA_KAMINARI",
          "powerChargeDamageRate": 20,
          "powerChargeGemDamageRate": 80,
          "powerChargeChangeGemDamageRate": 40,
          "extraAction1": {
            "timming": "TIME",
            "action": "WAZA",
            "value": 95,
            "wazano": "WAZA_OIKAZE"
          },
          "extraAction2": {
            "timming": "TIME",
            "action": "BOSS_STATUS_RESET",
            "value": 60,
            "wazano": "WAZA_NULL"
          },
          "extraAction3": {
            "timming": "NONE",
            "action": "NONE",
            "value": 0,
            "wazano": "WAZA_NULL"
          },
          "extraAction4": {
            "timming": "NONE",
            "action": "NONE",
            "value": 0,
            "wazano": "WAZA_NULL"
          },
          "extraAction5": {
            "timming": "NONE",
            "action": "NONE",
            "value": 0,
            "wazano": "WAZA_NULL"
          },
          "extraAction6": {
            "timming": "NONE",
            "action": "NONE",
            "value": 0,
            "wazano": "WAZA_NULL"
          },
          "doubleActionTrigerHp": 0,
          "doubleActionTrigerTime": 0,
          "doubleActionRate": 0
        },
        "raidTimeData": {
          "isActive": false,
          "gameLimit": 0,
          "clientLimit": 0,
          "commandLimit": 0,
          "pokeReviveTime": 0,
          "aiIntervalTime": 0,
          "aiIntervalRand": 0
        }
      }
    },
    {
      "raidEnemyInfo": {
        "romVer": "BOTH",
        "no": 14005,
        "deliveryGroupID": 0,
        "difficulty": 0,
        "rate": 100,
        "dropTableFix": 6567691901553146942,
        "dropTableRandom": 6567691901553146942,
        "captureRate": 1,
        "captureLv": 45,
        "bossPokePara": {
          "devId": "DEV_ARIADOSU",
          "formId": 0,
          "sex": "DEFAULT",
          "item": "ITEMID_NONE",
          "level": 45,
          "ballId": "NONE",
          "wazaType": "MANUAL",
          "waza1": {
            "wazaId": "WAZA_MUSIKUI",
            "pointUp": 0
          },
          "waza2": {
            "wazaId": "WAZA_SIZAAKUROSU",
            "pointUp": 0
          },
          "waza3": {
            "wazaId": "WAZA_DOKUDUKI",
            "pointUp": 0
          },
          "waza4": {
            "wazaId": "WAZA_KAGEUTI",
            "pointUp": 0
          },
          "gemType": "RANDOM",
          "seikaku": "DEFAULT",
          "tokusei": "RANDOM_123",
          "talentType": "V_NUM",
          "talentValue": {
            "hp": 0,
            "atk": 0,
            "def": 0,
            "spAtk": 0,
            "spDef": 0,
            "agi": 0
          },
          "talentVnum": 3,
          "effortValue": {
            "hp": 0,
            "atk": 0,
            "def": 0,
            "spAtk": 0,
            "spDef": 0,
            "agi": 0
          },
          "rareType": "DEFAULT",
          "scaleType": "RANDOM",
          "scaleValue": 0
        },
        "bossPokeSize": {
          "heightType": "RANDOM",
          "heigntValue": 0,
          "weightType": "RANDOM",
          "waightValue": 0,
          "scaleType": "RANDOM",
          "scaleValue": 0
        },
        "bossDesc": {
          "hpCoef": 1200,
          "powerChargeTrigerHp": 50,
          "powerChargeTrigerTime": 40,
          "powerChargeLimitTime": 9999,
          "powerChargeCancelDamage": 20,
          "powerChargePenaltyTime": 0,
          "powerChargePenaltyAction": "WAZA_KAMINARI",
          "powerChargeDamageRate": 20,
          "powerChargeGemDamageRate": 80,
          "powerChargeChangeGemDamageRate": 40,
          "extraAction1": {
            "timming": "TIME",
            "action": "WAZA",
            "value": 95,
            "wazano": "WAZA_NEBANEBANETTO"
          },
          "extraAction2": {
            "timming": "TIME",
            "action": "BOSS_STATUS_RESET",
            "value": 60,
            "wazano": "WAZA_NULL"
          },
          "extraAction3": {
            "timming": "NONE",
            "action": "NONE",
            "value": 0,
            "wazano": "WAZA_NULL"
          },
          "extraAction4": {
            "timming": "NONE",
            "action": "NONE",
            "value": 0,
            "wazano": "WAZA_NULL"
          },
          "extraAction5": {
            "timming": "NONE",
            "action": "NONE",
            "value": 0,
            "wazano": "WAZA_NULL"
          },
          "extraAction6": {
            "timming": "NONE",
            "action": "NONE",
            "value": 0,
            "wazano": "WAZA_NULL"
          },
          "doubleActionTrigerHp": 0,
          "doubleActionTrigerTime": 0,
          "doubleActionRate": 0
        },
        "raidTimeData": {
          "isActive": false,
          "gameLimit": 0,
          "clientLimit": 0,
          "commandLimit": 0,
          "pokeReviveTime": 0,
          "aiIntervalTime": 0,
          "aiIntervalRand": 0
        }
      }
    },
    {
      "raidEnemyInfo": {
        "romVer": "BOTH",
        "no": 14006,
        "deliveryGroupID": 0,
        "difficulty": 0,
        "rate": 100,
        "dropTableFix": 6567690802041518731,
        "dropTableRandom": 6567690802041518731,
        "captureRate": 1,
        "captureLv": 45,
        "bossPokePara": {
          "devId": "DEV_MAGUKARUGO",
          "formId": 0,
          "sex": "DEFAULT",
          "item": "ITEMID_NONE",
          "level": 45,
          "ballId": "NONE",
          "wazaType": "MANUAL",
          "waza1": {
            "wazaId": "WAZA_KAENHOUSYA",
            "pointUp": 0
          },
          "waza2": {
            "wazaId": "WAZA_GANSEKIHUUZI",
            "pointUp": 0
          },
          "waza3": {
            "wazaId": "WAZA_KATAKUNARU",
            "pointUp": 0
          },
          "waza4": {
            "wazaId": "WAZA_IWANADARE",
            "pointUp": 0
          },
          "gemType": "RANDOM",
          "seikaku": "DEFAULT",
          "tokusei": "RANDOM_123",
          "talentType": "V_NUM",
          "talentValue": {
            "hp": 0,
            "atk": 0,
            "def": 0,
            "spAtk": 0,
            "spDef": 0,
            "agi": 0
          },
          "talentVnum": 3,
          "effortValue": {
            "hp": 0,
            "atk": 0,
            "def": 0,
            "spAtk": 0,
            "spDef": 0,
            "agi": 0
          },
          "rareType": "DEFAULT",
          "scaleType": "RANDOM",
          "scaleValue": 0
        },
        "bossPokeSize": {
          "heightType": "RANDOM",
          "heigntValue": 0,
          "weightType": "RANDOM",
          "waightValue": 0,
          "scaleType": "RANDOM",
          "scaleValue": 0
        },
        "bossDesc": {
          "hpCoef": 1200,
          "powerChargeTrigerHp": 50,
          "powerChargeTrigerTime": 40,
          "powerChargeLimitTime": 9999,
          "powerChargeCancelDamage": 20,
          "powerChargePenaltyTime": 0,
          "powerChargePenaltyAction": "WAZA_KAMINARI",
          "powerChargeDamageRate": 20,
          "powerChargeGemDamageRate": 80,
          "powerChargeChangeGemDamageRate": 40,
          "extraAction1": {
            "timming": "TIME",
            "action": "WAZA",
            "value": 95,
            "wazano": "WAZA_NIHONBARE"
          },
          "extraAction2": {
            "timming": "HP",
            "action": "PLAYER_STATUS_RESET",
            "value": 60,
            "wazano": "WAZA_NULL"
          },
          "extraAction3": {
            "timming": "NONE",
            "action": "NONE",
            "value": 0,
            "wazano": "WAZA_NULL"
          },
          "extraAction4": {
            "timming": "NONE",
            "action": "NONE",
            "value": 0,
            "wazano": "WAZA_NULL"
          },
          "extraAction5": {
            "timming": "NONE",
            "action": "NONE",
            "value": 0,
            "wazano": "WAZA_NULL"
          },
          "extraAction6": {
            "timming": "NONE",
            "action": "NONE",
            "value": 0,
            "wazano": "WAZA_NULL"
          },
          "doubleActionTrigerHp": 0,
          "doubleActionTrigerTime": 0,
          "doubleActionRate": 0
        },
        "raidTimeData": {
          "isActive": false,
          "gameLimit": 0,
          "clientLimit": 0,
          "commandLimit": 0,
          "pokeReviveTime": 0,
          "aiIntervalTime": 0,
          "aiIntervalRand": 0
        }
      }
    },
    {
      "raidEnemyInfo": {
        "romVer": "BOTH",
        "no": 14007,
        "deliveryGroupID": 0,
        "difficulty": 0,
        "rate": 100,
        "dropTableFix": 6567689702529890520,
        "dropTableRandom": 6567689702529890520,
        "captureRate": 1,
        "captureLv": 45,
        "bossPokePara": {
          "devId": "DEV_INOMUU",
          "formId": 0,
          "sex": "DEFAULT",
          "item": "ITEMID_NONE",
          "level": 45,
          "ballId": "NONE",
          "wazaType": "MANUAL",
          "waza1": {
            "wazaId": "WAZA_KOORINOKIBA",
            "pointUp": 0
          },
          "waza2": {
            "wazaId": "WAZA_ZINARASI",
            "pointUp": 0
          },
          "waza3": {
            "wazaId": "WAZA_GENSINOTIKARA",
            "pointUp": 0
          },
          "waza4": {
            "wazaId": "WAZA_KOORINOTUBUTE",
            "pointUp": 0
          },
          "gemType": "RANDOM",
          "seikaku": "DEFAULT",
          "tokusei": "RANDOM_123",
          "talentType": "V_NUM",
          "talentValue": {
            "hp": 0,
            "atk": 0,
            "def": 0,
            "spAtk": 0,
            "spDef": 0,
            "agi": 0
          },
          "talentVnum": 3,
          "effortValue": {
            "hp": 0,
            "atk": 0,
            "def": 0,
            "spAtk": 0,
            "spDef": 0,
            "agi": 0
          },
          "rareType": "DEFAULT",
          "scaleType": "RANDOM",
          "scaleValue": 0
        },
        "bossPokeSize": {
          "heightType": "RANDOM",
          "heigntValue": 0,
          "weightType": "RANDOM",
          "waightValue": 0,
          "scaleType": "RANDOM",
          "scaleValue": 0
        },
        "bossDesc": {
          "hpCoef": 1200,
          "powerChargeTrigerHp": 50,
          "powerChargeTrigerTime": 40,
          "powerChargeLimitTime": 9999,
          "powerChargeCancelDamage": 20,
          "powerChargePenaltyTime": 0,
          "powerChargePenaltyAction": "WAZA_KAMINARI",
          "powerChargeDamageRate": 20,
          "powerChargeGemDamageRate": 80,
          "powerChargeChangeGemDamageRate": 40,
          "extraAction1": {
            "timming": "TIME",
            "action": "WAZA",
            "value": 95,
            "wazano": "WAZA_YUKIGESIKI"
          },
          "extraAction2": {
            "timming": "HP",
            "action": "PLAYER_STATUS_RESET",
            "value": 60,
            "wazano": "WAZA_NULL"
          },
          "extraAction3": {
            "timming": "NONE",
            "action": "NONE",
            "value": 0,
            "wazano": "WAZA_NULL"
          },
          "extraAction4": {
            "timming": "NONE",
            "action": "NONE",
            "value": 0,
            "wazano": "WAZA_NULL"
          },
          "extraAction5": {
            "timming": "NONE",
            "action": "NONE",
            "value": 0,
            "wazano": "WAZA_NULL"
          },
          "extraAction6": {
            "timming": "NONE",
            "action": "NONE",
            "value": 0,
            "wazano": "WAZA_NULL"
          },
          "doubleActionTrigerHp": 0,
          "doubleActionTrigerTime": 0,
          "doubleActionRate": 0
        },
        "raidTimeData": {
          "isActive": false,
          "gameLimit": 0,
          "clientLimit": 0,
          "commandLimit": 0,
          "pokeReviveTime": 0,
          "aiIntervalTime": 0,
          "aiIntervalRand": 0
        }
      }
    },
    {
      "raidEnemyInfo": {
        "romVer": "BOTH",
        "no": 14008,
        "deliveryGroupID": 0,
        "difficulty": 0,
        "rate": 100,
        "dropTableFix": 6567691901553146942,
        "dropTableRandom": 6567691901553146942,
        "captureRate": 1,
        "captureLv": 45,
        "bossPokePara": {
          "devId": "DEV_GURAENA",
          "formId": 0,
          "sex": "DEFAULT",
          "item": "ITEMID_NONE",
          "level": 45,
          "ballId": "NONE",
          "wazaType": "MANUAL",
          "waza1": {
            "wazaId": "WAZA_KAMIKUDAKU",
            "pointUp": 0
          },
          "waza2": {
            "wazaId": "WAZA_ZYARETUKU",
            "pointUp": 0
          },
          "waza3": {
            "wazaId": "WAZA_TOOBOE",
            "pointUp": 0
          },
          "waza4": {
            "wazaId": "WAZA_TOSSIN",
            "pointUp": 0
          },
          "gemType": "RANDOM",
          "seikaku": "DEFAULT",
          "tokusei": "RANDOM_123",
          "talentType": "V_NUM",
          "talentValue": {
            "hp": 0,
            "atk": 0,
            "def": 0,
            "spAtk": 0,
            "spDef": 0,
            "agi": 0
          },
          "talentVnum": 3,
          "effortValue": {
            "hp": 0,
            "atk": 0,
            "def": 0,
            "spAtk": 0,
            "spDef": 0,
            "agi": 0
          },
          "rareType": "DEFAULT",
          "scaleType": "RANDOM",
          "scaleValue": 0
        },
        "bossPokeSize": {
          "heightType": "RANDOM",
          "heigntValue": 0,
          "weightType": "RANDOM",
          "waightValue": 0,
          "scaleType": "RANDOM",
          "scaleValue": 0
        },
        "bossDesc": {
          "hpCoef": 1200,
          "powerChargeTrigerHp": 50,
          "powerChargeTrigerTime": 40,
          "powerChargeLimitTime": 9999,
          "powerChargeCancelDamage": 20,
          "powerChargePenaltyTime": 0,
          "powerChargePenaltyAction": "WAZA_KAMINARI",
          "powerChargeDamageRate": 20,
          "powerChargeGemDamageRate": 80,
          "powerChargeChangeGemDamageRate": 40,
          "extraAction1": {
            "timming": "TIME",
            "action": "WAZA",
            "value": 90,
            "wazano": "WAZA_TOOBOE"
          },
          "extraAction2": {
            "timming": "TIME",
            "action": "BOSS_STATUS_RESET",
            "value": 60,
            "wazano": "WAZA_NULL"
          },
          "extraAction3": {
            "timming": "NONE",
            "action": "NONE",
            "value": 0,
            "wazano": "WAZA_NULL"
          },
          "extraAction4": {
            "timming": "NONE",
            "action": "NONE",
            "value": 0,
            "wazano": "WAZA_NULL"
          },
          "extraAction5": {
            "timming": "NONE",
            "action": "NONE",
            "value": 0,
            "wazano": "WAZA_NULL"
          },
          "extraAction6": {
            "timming": "NONE",
            "action": "NONE",
            "value": 0,
            "wazano": "WAZA_NULL"
          },
          "doubleActionTrigerHp": 0,
          "doubleActionTrigerTime": 0,
          "doubleActionRate": 0
        },
        "raidTimeData": {
          "isActive": false,
          "gameLimit": 0,
          "clientLimit": 0,
          "commandLimit": 0,
          "pokeReviveTime": 0,
          "aiIntervalTime": 0,
          "aiIntervalRand": 0
        }
      }
    },
    {
      "raidEnemyInfo": {
        "romVer": "TYPE_A",
        "no": 14009,
        "deliveryGroupID": 0,
        "difficulty": 0,
        "rate": 100,
        "dropTableFix": 6567697399111287997,
        "dropTableRandom": 6567697399111287997,
        "captureRate": 1,
        "captureLv": 45,
        "bossPokePara": {
          "devId": "DEV_BARUBIITO",
          "formId": 0,
          "sex": "DEFAULT",
          "item": "ITEMID_NONE",
          "level": 45,
          "ballId": "NONE",
          "wazaType": "MANUAL",
          "waza1": {
            "wazaId": "WAZA_MUSINOSAZAMEKI",
            "pointUp": 0
          },
          "waza2": {
            "wazaId": "WAZA_GIGADOREIN",
            "pointUp": 0
          },
          "waza3": {
            "wazaId": "WAZA_DENKOUSEKKA",
            "pointUp": 0
          },
          "waza4": {
            "wazaId": "WAZA_SUPIIDOSUTAA",
            "pointUp": 0
          },
          "gemType": "RANDOM",
          "seikaku": "DEFAULT",
          "tokusei": "RANDOM_123",
          "talentType": "V_NUM",
          "talentValue": {
            "hp": 0,
            "atk": 0,
            "def": 0,
            "spAtk": 0,
            "spDef": 0,
            "agi": 0
          },
          "talentVnum": 3,
          "effortValue": {
            "hp": 0,
            "atk": 0,
            "def": 0,
            "spAtk": 0,
            "spDef": 0,
            "agi": 0
          },
          "rareType": "DEFAULT",
          "scaleType": "RANDOM",
          "scaleValue": 0
        },
        "bossPokeSize": {
          "heightType": "RANDOM",
          "heigntValue": 0,
          "weightType": "RANDOM",
          "waightValue": 0,
          "scaleType": "RANDOM",
          "scaleValue": 0
        },
        "bossDesc": {
          "hpCoef": 1200,
          "powerChargeTrigerHp": 50,
          "powerChargeTrigerTime": 40,
          "powerChargeLimitTime": 9999,
          "powerChargeCancelDamage": 20,
          "powerChargePenaltyTime": 0,
          "powerChargePenaltyAction": "WAZA_KAMINARI",
          "powerChargeDamageRate": 20,
          "powerChargeGemDamageRate": 80,
          "powerChargeChangeGemDamageRate": 40,
          "extraAction1": {
            "timming": "HP",
            "action": "BOSS_STATUS_RESET",
            "value": 70,
            "wazano": "WAZA_NULL"
          },
          "extraAction2": {
            "timming": "HP",
            "action": "WAZA",
            "value": 60,
            "wazano": "WAZA_HOTARUBI"
          },
          "extraAction3": {
            "timming": "NONE",
            "action": "NONE",
            "value": 0,
            "wazano": "WAZA_NULL"
          },
          "extraAction4": {
            "timming": "NONE",
            "action": "NONE",
            "value": 0,
            "wazano": "WAZA_NULL"
          },
          "extraAction5": {
            "timming": "NONE",
            "action": "NONE",
            "value": 0,
            "wazano": "WAZA_NULL"
          },
          "extraAction6": {
            "timming": "NONE",
            "action": "NONE",
            "value": 0,
            "wazano": "WAZA_NULL"
          },
          "doubleActionTrigerHp": 0,
          "doubleActionTrigerTime": 0,
          "doubleActionRate": 0
        },
        "raidTimeData": {
          "isActive": false,
          "gameLimit": 0,
          "clientLimit": 0,
          "commandLimit": 0,
          "pokeReviveTime": 0,
          "aiIntervalTime": 0,
          "aiIntervalRand": 0
        }
      }
    },
    {
      "raidEnemyInfo": {
        "romVer": "TYPE_B",
        "no": 14010,
        "deliveryGroupID": 0,
        "difficulty": 0,
        "rate": 100,
        "dropTableFix": 6567697399111287997,
        "dropTableRandom": 6567697399111287997,
        "captureRate": 1,
        "captureLv": 45,
        "bossPokePara": {
          "devId": "DEV_IRUMIIZE",
          "formId": 0,
          "sex": "DEFAULT",
          "item": "ITEMID_NONE",
          "level": 45,
          "ballId": "NONE",
          "wazaType": "MANUAL",
          "waza1": {
            "wazaId": "WAZA_MUSINOSAZAMEKI",
            "pointUp": 0
          },
          "waza2": {
            "wazaId": "WAZA_GIGADOREIN",
            "pointUp": 0
          },
          "waza3": {
            "wazaId": "WAZA_DENKOUSEKKA",
            "pointUp": 0
          },
          "waza4": {
            "wazaId": "WAZA_MEROMERO",
            "pointUp": 0
          },
          "gemType": "RANDOM",
          "seikaku": "DEFAULT",
          "tokusei": "RANDOM_123",
          "talentType": "V_NUM",
          "talentValue": {
            "hp": 0,
            "atk": 0,
            "def": 0,
            "spAtk": 0,
            "spDef": 0,
            "agi": 0
          },
          "talentVnum": 3,
          "effortValue": {
            "hp": 0,
            "atk": 0,
            "def": 0,
            "spAtk": 0,
            "spDef": 0,
            "agi": 0
          },
          "rareType": "DEFAULT",
          "scaleType": "RANDOM",
          "scaleValue": 0
        },
        "bossPokeSize": {
          "heightType": "RANDOM",
          "heigntValue": 0,
          "weightType": "RANDOM",
          "waightValue": 0,
          "scaleType": "RANDOM",
          "scaleValue": 0
        },
        "bossDesc": {
          "hpCoef": 1200,
          "powerChargeTrigerHp": 50,
          "powerChargeTrigerTime": 40,
          "powerChargeLimitTime": 9999,
          "powerChargeCancelDamage": 20,
          "powerChargePenaltyTime": 0,
          "powerChargePenaltyAction": "WAZA_KAMINARI",
          "powerChargeDamageRate": 20,
          "powerChargeGemDamageRate": 80,
          "powerChargeChangeGemDamageRate": 40,
          "extraAction1": {
            "timming": "TIME",
            "action": "WAZA",
            "value": 50,
            "wazano": "WAZA_MEROMERO"
          },
          "extraAction2": {
            "timming": "HP",
            "action": "NONE",
            "value": 0,
            "wazano": "WAZA_NULL"
          },
          "extraAction3": {
            "timming": "NONE",
            "action": "NONE",
            "value": 0,
            "wazano": "WAZA_NULL"
          },
          "extraAction4": {
            "timming": "NONE",
            "action": "NONE",
            "value": 0,
            "wazano": "WAZA_NULL"
          },
          "extraAction5": {
            "timming": "NONE",
            "action": "NONE",
            "value": 0,
            "wazano": "WAZA_NULL"
          },
          "extraAction6": {
            "timming": "NONE",
            "action": "NONE",
            "value": 0,
            "wazano": "WAZA_NULL"
          },
          "doubleActionTrigerHp": 0,
          "doubleActionTrigerTime": 0,
          "doubleActionRate": 0
        },
        "raidTimeData": {
          "isActive": false,
          "gameLimit": 0,
          "clientLimit": 0,
          "commandLimit": 0,
          "pokeReviveTime": 0,
          "aiIntervalTime": 0,
          "aiIntervalRand": 0
        }
      }
    },
    {
      "raidEnemyInfo": {
        "romVer": "BOTH",
        "no": 14011,
        "deliveryGroupID": 0,
        "difficulty": 0,
        "rate": 100,
        "dropTableFix": 6567691901553146942,
        "dropTableRandom": 6567691901553146942,
        "captureRate": 1,
        "captureLv": 45,
        "bossPokePara": {
          "devId": "DEV_SIZARIGAA",
          "formId": 0,
          "sex": "DEFAULT",
          "item": "ITEMID_NONE",
          "level": 45,
          "ballId": "NONE",
          "wazaType": "MANUAL",
          "waza1": {
            "wazaId": "WAZA_HATAKIOTOSU",
            "pointUp": 0
          },
          "waza2": {
            "wazaId": "WAZA_KURABUHANMAA",
            "pointUp": 0
          },
          "waza3": {
            "wazaId": "WAZA_AKUAJETTO",
            "pointUp": 0
          },
          "waza4": {
            "wazaId": "WAZA_TYOUHATU",
            "pointUp": 0
          },
          "gemType": "RANDOM",
          "seikaku": "DEFAULT",
          "tokusei": "RANDOM_123",
          "talentType": "V_NUM",
          "talentValue": {
            "hp": 0,
            "atk": 0,
            "def": 0,
            "spAtk": 0,
            "spDef": 0,
            "agi": 0
          },
          "talentVnum": 3,
          "effortValue": {
            "hp": 0,
            "atk": 0,
            "def": 0,
            "spAtk": 0,
            "spDef": 0,
            "agi": 0
          },
          "rareType": "DEFAULT",
          "scaleType": "RANDOM",
          "scaleValue": 0
        },
        "bossPokeSize": {
          "heightType": "RANDOM",
          "heigntValue": 0,
          "weightType": "RANDOM",
          "waightValue": 0,
          "scaleType": "RANDOM",
          "scaleValue": 0
        },
        "bossDesc": {
          "hpCoef": 1200,
          "powerChargeTrigerHp": 50,
          "powerChargeTrigerTime": 40,
          "powerChargeLimitTime": 9999,
          "powerChargeCancelDamage": 20,
          "powerChargePenaltyTime": 0,
          "powerChargePenaltyAction": "WAZA_KAMINARI",
          "powerChargeDamageRate": 20,
          "powerChargeGemDamageRate": 80,
          "powerChargeChangeGemDamageRate": 40,
          "extraAction1": {
            "timming": "TIME",
            "action": "WAZA",
            "value": 95,
            "wazano": "WAZA_TYOUHATU"
          },
          "extraAction2": {
            "timming": "HP",
            "action": "PLAYER_STATUS_RESET",
            "value": 60,
            "wazano": "WAZA_NULL"
          },
          "extraAction3": {
            "timming": "NONE",
            "action": "NONE",
            "value": 0,
            "wazano": "WAZA_NULL"
          },
          "extraAction4": {
            "timming": "NONE",
            "action": "NONE",
            "value": 0,
            "wazano": "WAZA_NULL"
          },
          "extraAction5": {
            "timming": "NONE",
            "action": "NONE",
            "value": 0,
            "wazano": "WAZA_NULL"
          },
          "extraAction6": {
            "timming": "NONE",
            "action": "NONE",
            "value": 0,
            "wazano": "WAZA_NULL"
          },
          "doubleActionTrigerHp": 0,
          "doubleActionTrigerTime": 0,
          "doubleActionRate": 0
        },
        "raidTimeData": {
          "isActive": false,
          "gameLimit": 0,
          "clientLimit": 0,
          "commandLimit": 0,
          "pokeReviveTime": 0,
          "aiIntervalTime": 0,
          "aiIntervalRand": 0
        }
      }
    },
    {
      "raidEnemyInfo": {
        "romVer": "BOTH",
        "no": 14012,
        "deliveryGroupID": 0,
        "difficulty": 0,
        "rate": 100,
        "dropTableFix": 6567690802041518731,
        "dropTableRandom": 6567690802041518731,
        "captureRate": 1,
        "captureLv": 45,
        "bossPokePara": {
          "devId": "DEV_SAMAYOORU",
          "formId": 0,
          "sex": "DEFAULT",
          "item": "ITEMID_NONE",
          "level": 45,
          "ballId": "NONE",
          "wazaType": "MANUAL",
          "waza1": {
            "wazaId": "WAZA_SYADOOPANTI",
            "pointUp": 0
          },
          "waza2": {
            "wazaId": "WAZA_ONIBI",
            "pointUp": 0
          },
          "waza3": {
            "wazaId": "WAZA_TATARIME",
            "pointUp": 0
          },
          "waza4": {
            "wazaId": "WAZA_AKUNOHADOU",
            "pointUp": 0
          },
          "gemType": "RANDOM",
          "seikaku": "DEFAULT",
          "tokusei": "RANDOM_123",
          "talentType": "V_NUM",
          "talentValue": {
            "hp": 0,
            "atk": 0,
            "def": 0,
            "spAtk": 0,
            "spDef": 0,
            "agi": 0
          },
          "talentVnum": 3,
          "effortValue": {
            "hp": 0,
            "atk": 0,
            "def": 0,
            "spAtk": 0,
            "spDef": 0,
            "agi": 0
          },
          "rareType": "DEFAULT",
          "scaleType": "RANDOM",
          "scaleValue": 0
        },
        "bossPokeSize": {
          "heightType": "RANDOM",
          "heigntValue": 0,
          "weightType": "RANDOM",
          "waightValue": 0,
          "scaleType": "RANDOM",
          "scaleValue": 0
        },
        "bossDesc": {
          "hpCoef": 1200,
          "powerChargeTrigerHp": 50,
          "powerChargeTrigerTime": 40,
          "powerChargeLimitTime": 9999,
          "powerChargeCancelDamage": 20,
          "powerChargePenaltyTime": 0,
          "powerChargePenaltyAction": "WAZA_KAMINARI",
          "powerChargeDamageRate": 20,
          "powerChargeGemDamageRate": 80,
          "powerChargeChangeGemDamageRate": 40,
          "extraAction1": {
            "timming": "TIME",
            "action": "PLAYER_STATUS_RESET",
            "value": 60,
            "wazano": "WAZA_NULL"
          },
          "extraAction2": {
            "timming": "HP",
            "action": "BOSS_STATUS_RESET",
            "value": 60,
            "wazano": "WAZA_NULL"
          },
          "extraAction3": {
            "timming": "NONE",
            "action": "NONE",
            "value": 0,
            "wazano": "WAZA_NULL"
          },
          "extraAction4": {
            "timming": "NONE",
            "action": "NONE",
            "value": 0,
            "wazano": "WAZA_NULL"
          },
          "extraAction5": {
            "timming": "NONE",
            "action": "NONE",
            "value": 0,
            "wazano": "WAZA_NULL"
          },
          "extraAction6": {
            "timming": "NONE",
            "action": "NONE",
            "value": 0,
            "wazano": "WAZA_NULL"
          },
          "doubleActionTrigerHp": 0,
          "doubleActionTrigerTime": 0,
          "doubleActionRate": 0
        },
        "raidTimeData": {
          "isActive": false,
          "gameLimit": 0,
          "clientLimit": 0,
          "commandLimit": 0,
          "pokeReviveTime": 0,
          "aiIntervalTime": 0,
          "aiIntervalRand": 0
        }
      }
    },
    {
      "raidEnemyInfo": {
        "romVer": "BOTH",
        "no": 14013,
        "deliveryGroupID": 0,
        "difficulty": 0,
        "rate": 100,
        "dropTableFix": 6567697399111287997,
        "dropTableRandom": 6567697399111287997,
        "captureRate": 1,
        "captureLv": 45,
        "bossPokePara": {
          "devId": "DEV_TIRIIN",
          "formId": 0,
          "sex": "DEFAULT",
          "item": "ITEMID_NONE",
          "level": 45,
          "ballId": "NONE",
          "wazaType": "MANUAL",
          "waza1": {
            "wazaId": "WAZA_SAIKOKINESISU",
            "pointUp": 0
          },
          "waza2": {
            "wazaId": "WAZA_ZINTUURIKI",
            "pointUp": 0
          },
          "waza3": {
            "wazaId": "WAZA_SYADOOBOORU",
            "pointUp": 0
          },
          "waza4": {
            "wazaId": "WAZA_SUPIIDOSUTAA",
            "pointUp": 0
          },
          "gemType": "RANDOM",
          "seikaku": "DEFAULT",
          "tokusei": "RANDOM_123",
          "talentType": "V_NUM",
          "talentValue": {
            "hp": 0,
            "atk": 0,
            "def": 0,
            "spAtk": 0,
            "spDef": 0,
            "agi": 0
          },
          "talentVnum": 3,
          "effortValue": {
            "hp": 0,
            "atk": 0,
            "def": 0,
            "spAtk": 0,
            "spDef": 0,
            "agi": 0
          },
          "rareType": "DEFAULT",
          "scaleType": "RANDOM",
          "scaleValue": 0
        },
        "bossPokeSize": {
          "heightType": "RANDOM",
          "heigntValue": 0,
          "weightType": "RANDOM",
          "waightValue": 0,
          "scaleType": "RANDOM",
          "scaleValue": 0
        },
        "bossDesc": {
          "hpCoef": 1200,
          "powerChargeTrigerHp": 50,
          "powerChargeTrigerTime": 40,
          "powerChargeLimitTime": 9999,
          "powerChargeCancelDamage": 20,
          "powerChargePenaltyTime": 0,
          "powerChargePenaltyAction": "WAZA_KAMINARI",
          "powerChargeDamageRate": 20,
          "powerChargeGemDamageRate": 80,
          "powerChargeChangeGemDamageRate": 40,
          "extraAction1": {
            "timming": "TIME",
            "action": "PLAYER_STATUS_RESET",
            "value": 60,
            "wazano": "WAZA_NULL"
          },
          "extraAction2": {
            "timming": "HP",
            "action": "BOSS_STATUS_RESET",
            "value": 60,
            "wazano": "WAZA_NULL"
          },
          "extraAction3": {
            "timming": "NONE",
            "action": "NONE",
            "value": 0,
            "wazano": "WAZA_NULL"
          },
          "extraAction4": {
            "timming": "NONE",
            "action": "NONE",
            "value": 0,
            "wazano": "WAZA_NULL"
          },
          "extraAction5": {
            "timming": "NONE",
            "action": "NONE",
            "value": 0,
            "wazano": "WAZA_NULL"
          },
          "extraAction6": {
            "timming": "NONE",
            "action": "NONE",
            "value": 0,
            "wazano": "WAZA_NULL"
          },
          "doubleActionTrigerHp": 0,
          "doubleActionTrigerTime": 0,
          "doubleActionRate": 0
        },
        "raidTimeData": {
          "isActive": false,
          "gameLimit": 0,
          "clientLimit": 0,
          "commandLimit": 0,
          "pokeReviveTime": 0,
          "aiIntervalTime": 0,
          "aiIntervalRand": 0
        }
      }
    },
    {
      "raidEnemyInfo": {
        "romVer": "BOTH",
        "no": 14014,
        "deliveryGroupID": 0,
        "difficulty": 0,
        "rate": 100,
        "dropTableFix": 6567691901553146942,
        "dropTableRandom": 6567691901553146942,
        "captureRate": 1,
        "captureLv": 45,
        "bossPokePara": {
          "devId": "DEV_HAHAKOMORI",
          "formId": 0,
          "sex": "DEFAULT",
          "item": "ITEMID_NONE",
          "level": 45,
          "ballId": "NONE",
          "wazaType": "MANUAL",
          "waza1": {
            "wazaId": "WAZA_SIZAAKUROSU",
            "pointUp": 0
          },
          "waza2": {
            "wazaId": "WAZA_RIIHUBUREEDO",
            "pointUp": 0
          },
          "waza3": {
            "wazaId": "WAZA_KUSAWAKE",
            "pointUp": 0
          },
          "waza4": {
            "wazaId": "WAZA_KETAGURI",
            "pointUp": 0
          },
          "gemType": "RANDOM",
          "seikaku": "DEFAULT",
          "tokusei": "RANDOM_123",
          "talentType": "V_NUM",
          "talentValue": {
            "hp": 0,
            "atk": 0,
            "def": 0,
            "spAtk": 0,
            "spDef": 0,
            "agi": 0
          },
          "talentVnum": 3,
          "effortValue": {
            "hp": 0,
            "atk": 0,
            "def": 0,
            "spAtk": 0,
            "spDef": 0,
            "agi": 0
          },
          "rareType": "DEFAULT",
          "scaleType": "RANDOM",
          "scaleValue": 0
        },
        "bossPokeSize": {
          "heightType": "RANDOM",
          "heigntValue": 0,
          "weightType": "RANDOM",
          "waightValue": 0,
          "scaleType": "RANDOM",
          "scaleValue": 0
        },
        "bossDesc": {
          "hpCoef": 1200,
          "powerChargeTrigerHp": 50,
          "powerChargeTrigerTime": 40,
          "powerChargeLimitTime": 9999,
          "powerChargeCancelDamage": 20,
          "powerChargePenaltyTime": 0,
          "powerChargePenaltyAction": "WAZA_KAMINARI",
          "powerChargeDamageRate": 20,
          "powerChargeGemDamageRate": 80,
          "powerChargeChangeGemDamageRate": 40,
          "extraAction1": {
            "timming": "TIME",
            "action": "WAZA",
            "value": 90,
            "wazano": "WAZA_GURASUFIIRUDO"
          },
          "extraAction2": {
            "timming": "TIME",
            "action": "WAZA",
            "value": 30,
            "wazano": "WAZA_GURASUSURAIDAA"
          },
          "extraAction3": {
            "timming": "NONE",
            "action": "NONE",
            "value": 0,
            "wazano": "WAZA_NULL"
          },
          "extraAction4": {
            "timming": "NONE",
            "action": "NONE",
            "value": 0,
            "wazano": "WAZA_NULL"
          },
          "extraAction5": {
            "timming": "NONE",
            "action": "NONE",
            "value": 0,
            "wazano": "WAZA_NULL"
          },
          "extraAction6": {
            "timming": "NONE",
            "action": "NONE",
            "value": 0,
            "wazano": "WAZA_NULL"
          },
          "doubleActionTrigerHp": 0,
          "doubleActionTrigerTime": 0,
          "doubleActionRate": 0
        },
        "raidTimeData": {
          "isActive": false,
          "gameLimit": 0,
          "clientLimit": 0,
          "commandLimit": 0,
          "pokeReviveTime": 0,
          "aiIntervalTime": 0,
          "aiIntervalRand": 0
        }
      }
    },
    {
      "raidEnemyInfo": {
        "romVer": "BOTH",
        "no": 14015,
        "deliveryGroupID": 0,
        "difficulty": 0,
        "rate": 100,
        "dropTableFix": 6567695200088031575,
        "dropTableRandom": 6567695200088031575,
        "captureRate": 1,
        "captureLv": 45,
        "bossPokePara": {
          "devId": "DEV_SUWANNA",
          "formId": 0,
          "sex": "DEFAULT",
          "item": "ITEMID_NONE",
          "level": 45,
          "ballId": "NONE",
          "wazaType": "MANUAL",
          "waza1": {
            "wazaId": "WAZA_NAMINORI",
            "pointUp": 0
          },
          "waza2": {
            "wazaId": "WAZA_EASURASSYU",
            "pointUp": 0
          },
          "waza3": {
            "wazaId": "WAZA_AMAGOI",
            "pointUp": 0
          },
          "waza4": {
            "wazaId": "WAZA_REITOUBIIMU",
            "pointUp": 0
          },
          "gemType": "RANDOM",
          "seikaku": "DEFAULT",
          "tokusei": "RANDOM_123",
          "talentType": "V_NUM",
          "talentValue": {
            "hp": 0,
            "atk": 0,
            "def": 0,
            "spAtk": 0,
            "spDef": 0,
            "agi": 0
          },
          "talentVnum": 3,
          "effortValue": {
            "hp": 0,
            "atk": 0,
            "def": 0,
            "spAtk": 0,
            "spDef": 0,
            "agi": 0
          },
          "rareType": "DEFAULT",
          "scaleType": "RANDOM",
          "scaleValue": 0
        },
        "bossPokeSize": {
          "heightType": "RANDOM",
          "heigntValue": 0,
          "weightType": "RANDOM",
          "waightValue": 0,
          "scaleType": "RANDOM",
          "scaleValue": 0
        },
        "bossDesc": {
          "hpCoef": 1200,
          "powerChargeTrigerHp": 50,
          "powerChargeTrigerTime": 40,
          "powerChargeLimitTime": 9999,
          "powerChargeCancelDamage": 20,
          "powerChargePenaltyTime": 0,
          "powerChargePenaltyAction": "WAZA_KAMINARI",
          "powerChargeDamageRate": 20,
          "powerChargeGemDamageRate": 80,
          "powerChargeChangeGemDamageRate": 40,
          "extraAction1": {
            "timming": "TIME",
            "action": "WAZA",
            "value": 90,
            "wazano": "WAZA_OIKAZE"
          },
          "extraAction2": {
            "timming": "HP",
            "action": "WAZA",
            "value": 10,
            "wazano": "WAZA_BOUHUU"
          },
          "extraAction3": {
            "timming": "NONE",
            "action": "NONE",
            "value": 0,
            "wazano": "WAZA_NULL"
          },
          "extraAction4": {
            "timming": "NONE",
            "action": "NONE",
            "value": 0,
            "wazano": "WAZA_NULL"
          },
          "extraAction5": {
            "timming": "NONE",
            "action": "NONE",
            "value": 0,
            "wazano": "WAZA_NULL"
          },
          "extraAction6": {
            "timming": "NONE",
            "action": "NONE",
            "value": 0,
            "wazano": "WAZA_NULL"
          },
          "doubleActionTrigerHp": 0,
          "doubleActionTrigerTime": 0,
          "doubleActionRate": 0
        },
        "raidTimeData": {
          "isActive": false,
          "gameLimit": 0,
          "clientLimit": 0,
          "commandLimit": 0,
          "pokeReviveTime": 0,
          "aiIntervalTime": 0,
          "aiIntervalRand": 0
        }
      }
    },
    {
      "raidEnemyInfo": {
        "romVer": "BOTH",
        "no": 14016,
        "deliveryGroupID": 0,
        "difficulty": 0,
        "rate": 100,
        "dropTableFix": 6567697399111287997,
        "dropTableRandom": 6567697399111287997,
        "captureRate": 1,
        "captureLv": 45,
        "bossPokePara": {
          "devId": "DEV_RANPURAA",
          "formId": 0,
          "sex": "DEFAULT",
          "item": "ITEMID_NONE",
          "level": 45,
          "ballId": "NONE",
          "wazaType": "MANUAL",
          "waza1": {
            "wazaId": "WAZA_NEPPUU",
            "pointUp": 0
          },
          "waza2": {
            "wazaId": "WAZA_SYADOOBOORU",
            "pointUp": 0
          },
          "waza3": {
            "wazaId": "WAZA_ONIBI",
            "pointUp": 0
          },
          "waza4": {
            "wazaId": "WAZA_NAITOHEDDO",
            "pointUp": 0
          },
          "gemType": "RANDOM",
          "seikaku": "DEFAULT",
          "tokusei": "RANDOM_123",
          "talentType": "V_NUM",
          "talentValue": {
            "hp": 0,
            "atk": 0,
            "def": 0,
            "spAtk": 0,
            "spDef": 0,
            "agi": 0
          },
          "talentVnum": 3,
          "effortValue": {
            "hp": 0,
            "atk": 0,
            "def": 0,
            "spAtk": 0,
            "spDef": 0,
            "agi": 0
          },
          "rareType": "DEFAULT",
          "scaleType": "RANDOM",
          "scaleValue": 0
        },
        "bossPokeSize": {
          "heightType": "RANDOM",
          "heigntValue": 0,
          "weightType": "RANDOM",
          "waightValue": 0,
          "scaleType": "RANDOM",
          "scaleValue": 0
        },
        "bossDesc": {
          "hpCoef": 1200,
          "powerChargeTrigerHp": 50,
          "powerChargeTrigerTime": 40,
          "powerChargeLimitTime": 9999,
          "powerChargeCancelDamage": 20,
          "powerChargePenaltyTime": 0,
          "powerChargePenaltyAction": "WAZA_KAMINARI",
          "powerChargeDamageRate": 20,
          "powerChargeGemDamageRate": 80,
          "powerChargeChangeGemDamageRate": 40,
          "extraAction1": {
            "timming": "HP",
            "action": "PLAYER_STATUS_RESET",
            "value": 50,
            "wazano": "WAZA_NULL"
          },
          "extraAction2": {
            "timming": "HP",
            "action": "PLAYER_STATUS_RESET",
            "value": 60,
            "wazano": "WAZA_NULL"
          },
          "extraAction3": {
            "timming": "NONE",
            "action": "NONE",
            "value": 0,
            "wazano": "WAZA_NULL"
          },
          "extraAction4": {
            "timming": "NONE",
            "action": "NONE",
            "value": 0,
            "wazano": "WAZA_NULL"
          },
          "extraAction5": {
            "timming": "NONE",
            "action": "NONE",
            "value": 0,
            "wazano": "WAZA_NULL"
          },
          "extraAction6": {
            "timming": "NONE",
            "action": "NONE",
            "value": 0,
            "wazano": "WAZA_NULL"
          },
          "doubleActionTrigerHp": 0,
          "doubleActionTrigerTime": 0,
          "doubleActionRate": 0
        },
        "raidTimeData": {
          "isActive": false,
          "gameLimit": 0,
          "clientLimit": 0,
          "commandLimit": 0,
          "pokeReviveTime": 0,
          "aiIntervalTime": 0,
          "aiIntervalRand": 0
        }
      }
    },
    {
      "raidEnemyInfo": {
        "romVer": "BOTH",
        "no": 14017,
        "deliveryGroupID": 0,
        "difficulty": 0,
        "rate": 100,
        "dropTableFix": 6567690802041518731,
        "dropTableRandom": 6567690802041518731,
        "captureRate": 1,
        "captureLv": 45,
        "bossPokePara": {
          "devId": "DEV_MERESII",
          "formId": 0,
          "sex": "DEFAULT",
          "item": "ITEMID_NONE",
          "level": 45,
          "ballId": "NONE",
          "wazaType": "MANUAL",
          "waza1": {
            "wazaId": "WAZA_PAWAAJEMU",
            "pointUp": 0
          },
          "waza2": {
            "wazaId": "WAZA_MUUNFOOSU",
            "pointUp": 0
          },
          "waza3": {
            "wazaId": "WAZA_SUTOONEZZI",
            "pointUp": 0
          },
          "waza4": {
            "wazaId": "WAZA_HIKARINOKABE",
            "pointUp": 0
          },
          "gemType": "RANDOM",
          "seikaku": "DEFAULT",
          "tokusei": "RANDOM_123",
          "talentType": "V_NUM",
          "talentValue": {
            "hp": 0,
            "atk": 0,
            "def": 0,
            "spAtk": 0,
            "spDef": 0,
            "agi": 0
          },
          "talentVnum": 3,
          "effortValue": {
            "hp": 0,
            "atk": 0,
            "def": 0,
            "spAtk": 0,
            "spDef": 0,
            "agi": 0
          },
          "rareType": "DEFAULT",
          "scaleType": "RANDOM",
          "scaleValue": 0
        },
        "bossPokeSize": {
          "heightType": "RANDOM",
          "heigntValue": 0,
          "weightType": "RANDOM",
          "waightValue": 0,
          "scaleType": "RANDOM",
          "scaleValue": 0
        },
        "bossDesc": {
          "hpCoef": 1200,
          "powerChargeTrigerHp": 50,
          "powerChargeTrigerTime": 40,
          "powerChargeLimitTime": 9999,
          "powerChargeCancelDamage": 20,
          "powerChargePenaltyTime": 0,
          "powerChargePenaltyAction": "WAZA_KAMINARI",
          "powerChargeDamageRate": 20,
          "powerChargeGemDamageRate": 80,
          "powerChargeChangeGemDamageRate": 40,
          "extraAction1": {
            "timming": "HP",
            "action": "WAZA",
            "value": 90,
            "wazano": "WAZA_RIHUREKUTAA"
          },
          "extraAction2": {
            "timming": "HP",
            "action": "PLAYER_STATUS_RESET",
            "value": 60,
            "wazano": "WAZA_NULL"
          },
          "extraAction3": {
            "timming": "NONE",
            "action": "NONE",
            "value": 0,
            "wazano": "WAZA_NULL"
          },
          "extraAction4": {
            "timming": "NONE",
            "action": "NONE",
            "value": 0,
            "wazano": "WAZA_NULL"
          },
          "extraAction5": {
            "timming": "NONE",
            "action": "NONE",
            "value": 0,
            "wazano": "WAZA_NULL"
          },
          "extraAction6": {
            "timming": "NONE",
            "action": "NONE",
            "value": 0,
            "wazano": "WAZA_NULL"
          },
          "doubleActionTrigerHp": 0,
          "doubleActionTrigerTime": 0,
          "doubleActionRate": 0
        },
        "raidTimeData": {
          "isActive": false,
          "gameLimit": 0,
          "clientLimit": 0,
          "commandLimit": 0,
          "pokeReviveTime": 0,
          "aiIntervalTime": 0,
          "aiIntervalRand": 0
        }
      }
    },
    {
      "raidEnemyInfo": {
        "romVer": "BOTH",
        "no": 14018,
        "deliveryGroupID": 0,
        "difficulty": 0,
        "rate": 100,
        "dropTableFix": 6567696299599659786,
        "dropTableRandom": 6567696299599659786,
        "captureRate": 1,
        "captureLv": 45,
        "bossPokePara": {
          "devId": "DEV_ABURIBON",
          "formId": 0,
          "sex": "DEFAULT",
          "item": "ITEMID_NONE",
          "level": 45,
          "ballId": "NONE",
          "wazaType": "MANUAL",
          "waza1": {
            "wazaId": "WAZA_KAHUNDANGO",
            "pointUp": 0
          },
          "waza2": {
            "wazaId": "WAZA_MUUNFOOSU",
            "pointUp": 0
          },
          "waza3": {
            "wazaId": "WAZA_MUSINOSAZAMEKI",
            "pointUp": 0
          },
          "waza4": {
            "wazaId": "WAZA_SIBIREGONA",
            "pointUp": 0
          },
          "gemType": "RANDOM",
          "seikaku": "DEFAULT",
          "tokusei": "RANDOM_123",
          "talentType": "V_NUM",
          "talentValue": {
            "hp": 0,
            "atk": 0,
            "def": 0,
            "spAtk": 0,
            "spDef": 0,
            "agi": 0
          },
          "talentVnum": 3,
          "effortValue": {
            "hp": 0,
            "atk": 0,
            "def": 0,
            "spAtk": 0,
            "spDef": 0,
            "agi": 0
          },
          "rareType": "DEFAULT",
          "scaleType": "RANDOM",
          "scaleValue": 0
        },
        "bossPokeSize": {
          "heightType": "RANDOM",
          "heigntValue": 0,
          "weightType": "RANDOM",
          "waightValue": 0,
          "scaleType": "RANDOM",
          "scaleValue": 0
        },
        "bossDesc": {
          "hpCoef": 1200,
          "powerChargeTrigerHp": 50,
          "powerChargeTrigerTime": 40,
          "powerChargeLimitTime": 9999,
          "powerChargeCancelDamage": 20,
          "powerChargePenaltyTime": 0,
          "powerChargePenaltyAction": "WAZA_KAMINARI",
          "powerChargeDamageRate": 20,
          "powerChargeGemDamageRate": 80,
          "powerChargeChangeGemDamageRate": 40,
          "extraAction1": {
            "timming": "HP",
            "action": "BOSS_STATUS_RESET",
            "value": 70,
            "wazano": "WAZA_NULL"
          },
          "extraAction2": {
            "timming": "HP",
            "action": "WAZA",
            "value": 60,
            "wazano": "WAZA_TYOUNOMAI"
          },
          "extraAction3": {
            "timming": "NONE",
            "action": "NONE",
            "value": 0,
            "wazano": "WAZA_NULL"
          },
          "extraAction4": {
            "timming": "NONE",
            "action": "NONE",
            "value": 0,
            "wazano": "WAZA_NULL"
          },
          "extraAction5": {
            "timming": "NONE",
            "action": "NONE",
            "value": 0,
            "wazano": "WAZA_NULL"
          },
          "extraAction6": {
            "timming": "NONE",
            "action": "NONE",
            "value": 0,
            "wazano": "WAZA_NULL"
          },
          "doubleActionTrigerHp": 0,
          "doubleActionTrigerTime": 0,
          "doubleActionRate": 0
        },
        "raidTimeData": {
          "isActive": false,
          "gameLimit": 0,
          "clientLimit": 0,
          "commandLimit": 0,
          "pokeReviveTime": 0,
          "aiIntervalTime": 0,
          "aiIntervalRand": 0
        }
      }
    },
    {
      "raidEnemyInfo": {
        "romVer": "BOTH",
        "no": 14019,
        "deliveryGroupID": 0,
        "difficulty": 0,
        "rate": 100,
        "dropTableFix": 6567690802041518731,
        "dropTableRandom": 6567690802041518731,
        "captureRate": 1,
        "captureLv": 45,
        "bossPokePara": {
          "devId": "DEV_ZYARANGO",
          "formId": 0,
          "sex": "DEFAULT",
          "item": "ITEMID_NONE",
          "level": 45,
          "ballId": "NONE",
          "wazaType": "MANUAL",
          "waza1": {
            "wazaId": "WAZA_DORAGONKUROO",
            "pointUp": 0
          },
          "waza2": {
            "wazaId": "WAZA_IYANAOTO",
            "pointUp": 0
          },
          "waza3": {
            "wazaId": "WAZA_INFAITO",
            "pointUp": 0
          },
          "waza4": {
            "wazaId": "WAZA_METARUKUROO",
            "pointUp": 0
          },
          "gemType": "RANDOM",
          "seikaku": "DEFAULT",
          "tokusei": "RANDOM_123",
          "talentType": "V_NUM",
          "talentValue": {
            "hp": 0,
            "atk": 0,
            "def": 0,
            "spAtk": 0,
            "spDef": 0,
            "agi": 0
          },
          "talentVnum": 3,
          "effortValue": {
            "hp": 0,
            "atk": 0,
            "def": 0,
            "spAtk": 0,
            "spDef": 0,
            "agi": 0
          },
          "rareType": "DEFAULT",
          "scaleType": "RANDOM",
          "scaleValue": 0
        },
        "bossPokeSize": {
          "heightType": "RANDOM",
          "heigntValue": 0,
          "weightType": "RANDOM",
          "waightValue": 0,
          "scaleType": "RANDOM",
          "scaleValue": 0
        },
        "bossDesc": {
          "hpCoef": 1200,
          "powerChargeTrigerHp": 50,
          "powerChargeTrigerTime": 40,
          "powerChargeLimitTime": 9999,
          "powerChargeCancelDamage": 20,
          "powerChargePenaltyTime": 0,
          "powerChargePenaltyAction": "WAZA_KAMINARI",
          "powerChargeDamageRate": 20,
          "powerChargeGemDamageRate": 80,
          "powerChargeChangeGemDamageRate": 40,
          "extraAction1": {
            "timming": "HP",
            "action": "PLAYER_STATUS_RESET",
            "value": 50,
            "wazano": "WAZA_NULL"
          },
          "extraAction2": {
            "timming": "HP",
            "action": "PLAYER_STATUS_RESET",
            "value": 60,
            "wazano": "WAZA_NULL"
          },
          "extraAction3": {
            "timming": "NONE",
            "action": "NONE",
            "value": 0,
            "wazano": "WAZA_NULL"
          },
          "extraAction4": {
            "timming": "NONE",
            "action": "NONE",
            "value": 0,
            "wazano": "WAZA_NULL"
          },
          "extraAction5": {
            "timming": "NONE",
            "action": "NONE",
            "value": 0,
            "wazano": "WAZA_NULL"
          },
          "extraAction6": {
            "timming": "NONE",
            "action": "NONE",
            "value": 0,
            "wazano": "WAZA_NULL"
          },
          "doubleActionTrigerHp": 0,
          "doubleActionTrigerTime": 0,
          "doubleActionRate": 0
        },
        "raidTimeData": {
          "isActive": false,
          "gameLimit": 0,
          "clientLimit": 0,
          "commandLimit": 0,
          "pokeReviveTime": 0,
          "aiIntervalTime": 0,
          "aiIntervalRand": 0
        }
      }
    },
    {
      "raidEnemyInfo": {
        "romVer": "TYPE_A",
        "no": 14020,
        "deliveryGroupID": 0,
        "difficulty": 0,
        "rate": 100,
        "dropTableFix": 6567689702529890520,
        "dropTableRandom": 6567689702529890520,
        "captureRate": 1,
        "captureLv": 45,
        "bossPokePara": {
          "devId": "DEV_UUU",
          "formId": 0,
          "sex": "DEFAULT",
          "item": "ITEMID_NONE",
          "level": 45,
          "ballId": "NONE",
          "wazaType": "MANUAL",
          "waza1": {
            "wazaId": "WAZA_EASURASSYU",
            "pointUp": 0
          },
          "waza2": {
            "wazaId": "WAZA_HIYAMIZU",
            "pointUp": 0
          },
          "waza3": {
            "wazaId": "WAZA_BOUHUU",
            "pointUp": 0
          },
          "waza4": {
            "wazaId": "WAZA_REITOUBIIMU",
            "pointUp": 0
          },
          "gemType": "RANDOM",
          "seikaku": "DEFAULT",
          "tokusei": "RANDOM_123",
          "talentType": "V_NUM",
          "talentValue": {
            "hp": 0,
            "atk": 0,
            "def": 0,
            "spAtk": 0,
            "spDef": 0,
            "agi": 0
          },
          "talentVnum": 3,
          "effortValue": {
            "hp": 0,
            "atk": 0,
            "def": 0,
            "spAtk": 0,
            "spDef": 0,
            "agi": 0
          },
          "rareType": "DEFAULT",
          "scaleType": "RANDOM",
          "scaleValue": 0
        },
        "bossPokeSize": {
          "heightType": "RANDOM",
          "heigntValue": 0,
          "weightType": "RANDOM",
          "waightValue": 0,
          "scaleType": "RANDOM",
          "scaleValue": 0
        },
        "bossDesc": {
          "hpCoef": 1200,
          "powerChargeTrigerHp": 50,
          "powerChargeTrigerTime": 40,
          "powerChargeLimitTime": 9999,
          "powerChargeCancelDamage": 20,
          "powerChargePenaltyTime": 0,
          "powerChargePenaltyAction": "WAZA_KAMINARI",
          "powerChargeDamageRate": 20,
          "powerChargeGemDamageRate": 80,
          "powerChargeChangeGemDamageRate": 40,
          "extraAction1": {
            "timming": "HP",
            "action": "WAZA",
            "value": 80,
            "wazano": "WAZA_FEZAADANSU"
          },
          "extraAction2": {
            "timming": "HP",
            "action": "PLAYER_STATUS_RESET",
            "value": 60,
            "wazano": "WAZA_NULL"
          },
          "extraAction3": {
            "timming": "NONE",
            "action": "NONE",
            "value": 0,
            "wazano": "WAZA_NULL"
          },
          "extraAction4": {
            "timming": "NONE",
            "action": "NONE",
            "value": 0,
            "wazano": "WAZA_NULL"
          },
          "extraAction5": {
            "timming": "NONE",
            "action": "NONE",
            "value": 0,
            "wazano": "WAZA_NULL"
          },
          "extraAction6": {
            "timming": "NONE",
            "action": "NONE",
            "value": 0,
            "wazano": "WAZA_NULL"
          },
          "doubleActionTrigerHp": 0,
          "doubleActionTrigerTime": 0,
          "doubleActionRate": 0
        },
        "raidTimeData": {
          "isActive": false,
          "gameLimit": 0,
          "clientLimit": 0,
          "commandLimit": 0,
          "pokeReviveTime": 0,
          "aiIntervalTime": 0,
          "aiIntervalRand": 0
        }
      }
    },
    {
      "raidEnemyInfo": {
        "romVer": "TYPE_B",
        "no": 14021,
        "deliveryGroupID": 0,
        "difficulty": 0,
        "rate": 100,
        "dropTableFix": 6567691901553146942,
        "dropTableRandom": 6567691901553146942,
        "captureRate": 1,
        "captureLv": 45,
        "bossPokePara": {
          "devId": "DEV_MORUPEKO",
          "formId": 0,
          "sex": "DEFAULT",
          "item": "ITEMID_NONE",
          "level": 45,
          "ballId": "NONE",
          "wazaType": "MANUAL",
          "waza1": {
            "wazaId": "WAZA_OORAGURUMA",
            "pointUp": 0
          },
          "waza2": {
            "wazaId": "WAZA_UPPUNBARASI",
            "pointUp": 0
          },
          "waza3": {
            "wazaId": "WAZA_ZYUUDEN",
            "pointUp": 0
          },
          "waza4": {
            "wazaId": "WAZA_TANEBAKUDAN",
            "pointUp": 0
          },
          "gemType": "RANDOM",
          "seikaku": "DEFAULT",
          "tokusei": "RANDOM_123",
          "talentType": "V_NUM",
          "talentValue": {
            "hp": 0,
            "atk": 0,
            "def": 0,
            "spAtk": 0,
            "spDef": 0,
            "agi": 0
          },
          "talentVnum": 3,
          "effortValue": {
            "hp": 0,
            "atk": 0,
            "def": 0,
            "spAtk": 0,
            "spDef": 0,
            "agi": 0
          },
          "rareType": "DEFAULT",
          "scaleType": "RANDOM",
          "scaleValue": 0
        },
        "bossPokeSize": {
          "heightType": "RANDOM",
          "heigntValue": 0,
          "weightType": "RANDOM",
          "waightValue": 0,
          "scaleType": "RANDOM",
          "scaleValue": 0
        },
        "bossDesc": {
          "hpCoef": 1200,
          "powerChargeTrigerHp": 50,
          "powerChargeTrigerTime": 40,
          "powerChargeLimitTime": 9999,
          "powerChargeCancelDamage": 20,
          "powerChargePenaltyTime": 0,
          "powerChargePenaltyAction": "WAZA_KAMINARI",
          "powerChargeDamageRate": 20,
          "powerChargeGemDamageRate": 80,
          "powerChargeChangeGemDamageRate": 40,
          "extraAction1": {
            "timming": "HP",
            "action": "WAZA",
            "value": 80,
            "wazano": "WAZA_EREKIFIIRUDO"
          },
          "extraAction2": {
            "timming": "HP",
            "action": "PLAYER_STATUS_RESET",
            "value": 60,
            "wazano": "WAZA_NULL"
          },
          "extraAction3": {
            "timming": "NONE",
            "action": "NONE",
            "value": 0,
            "wazano": "WAZA_NULL"
          },
          "extraAction4": {
            "timming": "NONE",
            "action": "NONE",
            "value": 0,
            "wazano": "WAZA_NULL"
          },
          "extraAction5": {
            "timming": "NONE",
            "action": "NONE",
            "value": 0,
            "wazano": "WAZA_NULL"
          },
          "extraAction6": {
            "timming": "NONE",
            "action": "NONE",
            "value": 0,
            "wazano": "WAZA_NULL"
          },
          "doubleActionTrigerHp": 0,
          "doubleActionTrigerTime": 0,
          "doubleActionRate": 0
        },
        "raidTimeData": {
          "isActive": false,
          "gameLimit": 0,
          "clientLimit": 0,
          "commandLimit": 0,
          "pokeReviveTime": 0,
          "aiIntervalTime": 0,
          "aiIntervalRand": 0
        }
      }
    },
    {
      "raidEnemyInfo": {
        "romVer": "BOTH",
        "no": 14022,
        "deliveryGroupID": 0,
        "difficulty": 0,
        "rate": 100,
        "dropTableFix": 6567689702529890520,
        "dropTableRandom": 6567689702529890520,
        "captureRate": 1,
        "captureLv": 45,
        "bossPokePara": {
          "devId": "DEV_NUOO",
          "formId": 0,
          "sex": "DEFAULT",
          "item": "ITEMID_NONE",
          "level": 45,
          "ballId": "NONE",
          "wazaType": "MANUAL",
          "waza1": {
            "wazaId": "WAZA_AKUABUREIKU",
            "pointUp": 0
          },
          "waza2": {
            "wazaId": "WAZA_ZISIN",
            "pointUp": 0
          },
          "waza3": {
            "wazaId": "WAZA_DOKUDOKU",
            "pointUp": 0
          },
          "waza4": {
            "wazaId": "WAZA_TAKUWAERU",
            "pointUp": 0
          },
          "gemType": "RANDOM",
          "seikaku": "DEFAULT",
          "tokusei": "RANDOM_123",
          "talentType": "V_NUM",
          "talentValue": {
            "hp": 0,
            "atk": 0,
            "def": 0,
            "spAtk": 0,
            "spDef": 0,
            "agi": 0
          },
          "talentVnum": 3,
          "effortValue": {
            "hp": 0,
            "atk": 0,
            "def": 0,
            "spAtk": 0,
            "spDef": 0,
            "agi": 0
          },
          "rareType": "DEFAULT",
          "scaleType": "RANDOM",
          "scaleValue": 0
        },
        "bossPokeSize": {
          "heightType": "RANDOM",
          "heigntValue": 0,
          "weightType": "RANDOM",
          "waightValue": 0,
          "scaleType": "RANDOM",
          "scaleValue": 0
        },
        "bossDesc": {
          "hpCoef": 1200,
          "powerChargeTrigerHp": 50,
          "powerChargeTrigerTime": 40,
          "powerChargeLimitTime": 9999,
          "powerChargeCancelDamage": 20,
          "powerChargePenaltyTime": 0,
          "powerChargePenaltyAction": "WAZA_KAMINARI",
          "powerChargeDamageRate": 20,
          "powerChargeGemDamageRate": 80,
          "powerChargeChangeGemDamageRate": 40,
          "extraAction1": {
            "timming": "TIME",
            "action": "PLAYER_STATUS_RESET",
            "value": 90,
            "wazano": "WAZA_NULL"
          },
          "extraAction2": {
            "timming": "HP",
            "action": "BOSS_STATUS_RESET",
            "value": 60,
            "wazano": "WAZA_NULL"
          },
          "extraAction3": {
            "timming": "NONE",
            "action": "NONE",
            "value": 0,
            "wazano": "WAZA_NULL"
          },
          "extraAction4": {
            "timming": "NONE",
            "action": "NONE",
            "value": 0,
            "wazano": "WAZA_NULL"
          },
          "extraAction5": {
            "timming": "NONE",
            "action": "NONE",
            "value": 0,
            "wazano": "WAZA_NULL"
          },
          "extraAction6": {
            "timming": "NONE",
            "action": "NONE",
            "value": 0,
            "wazano": "WAZA_NULL"
          },
          "doubleActionTrigerHp": 0,
          "doubleActionTrigerTime": 0,
          "doubleActionRate": 0
        },
        "raidTimeData": {
          "isActive": false,
          "gameLimit": 0,
          "clientLimit": 0,
          "commandLimit": 0,
          "pokeReviveTime": 0,
          "aiIntervalTime": 0,
          "aiIntervalRand": 0
        }
      }
    },
    {
      "raidEnemyInfo": {
        "romVer": "BOTH",
        "no": 14023,
        "deliveryGroupID": 0,
        "difficulty": 0,
        "rate": 100,
        "dropTableFix": 6567690802041518731,
        "dropTableRandom": 6567690802041518731,
        "captureRate": 1,
        "captureLv": 45,
        "bossPokePara": {
          "devId": "DEV_KAZITTYU2",
          "formId": 0,
          "sex": "DEFAULT",
          "item": "ITEMID_NONE",
          "level": 45,
          "ballId": "NONE",
          "wazaType": "MANUAL",
          "waza1": {
            "wazaId": "WAZA_MITSUAMEKOTO",
            "pointUp": 0
          },
          "waza2": {
            "wazaId": "WAZA_RYUUNOIBUKI",
            "pointUp": 0
          },
          "waza3": {
            "wazaId": "WAZA_DABURUATAKKU",
            "pointUp": 0
          },
          "waza4": {
            "wazaId": "WAZA_ENAZIIBOORU",
            "pointUp": 0
          },
          "gemType": "RANDOM",
          "seikaku": "DEFAULT",
          "tokusei": "RANDOM_123",
          "talentType": "V_NUM",
          "talentValue": {
            "hp": 0,
            "atk": 0,
            "def": 0,
            "spAtk": 0,
            "spDef": 0,
            "agi": 0
          },
          "talentVnum": 3,
          "effortValue": {
            "hp": 0,
            "atk": 0,
            "def": 0,
            "spAtk": 0,
            "spDef": 0,
            "agi": 0
          },
          "rareType": "DEFAULT",
          "scaleType": "RANDOM",
          "scaleValue": 0
        },
        "bossPokeSize": {
          "heightType": "RANDOM",
          "heigntValue": 0,
          "weightType": "RANDOM",
          "waightValue": 0,
          "scaleType": "RANDOM",
          "scaleValue": 0
        },
        "bossDesc": {
          "hpCoef": 1200,
          "powerChargeTrigerHp": 50,
          "powerChargeTrigerTime": 40,
          "powerChargeLimitTime": 9999,
          "powerChargeCancelDamage": 20,
          "powerChargePenaltyTime": 0,
          "powerChargePenaltyAction": "WAZA_KAMINARI",
          "powerChargeDamageRate": 20,
          "powerChargeGemDamageRate": 80,
          "powerChargeChangeGemDamageRate": 40,
          "extraAction1": {
            "timming": "TIME",
            "action": "WAZA",
            "value": 90,
            "wazano": "WAZA_MITSUAMEKOTO"
          },
          "extraAction2": {
            "timming": "HP",
            "action": "BOSS_STATUS_RESET",
            "value": 60,
            "wazano": "WAZA_NULL"
          },
          "extraAction3": {
            "timming": "NONE",
            "action": "NONE",
            "value": 0,
            "wazano": "WAZA_NULL"
          },
          "extraAction4": {
            "timming": "NONE",
            "action": "NONE",
            "value": 0,
            "wazano": "WAZA_NULL"
          },
          "extraAction5": {
            "timming": "NONE",
            "action": "NONE",
            "value": 0,
            "wazano": "WAZA_NULL"
          },
          "extraAction6": {
            "timming": "NONE",
            "action": "NONE",
            "value": 0,
            "wazano": "WAZA_NULL"
          },
          "doubleActionTrigerHp": 0,
          "doubleActionTrigerTime": 0,
          "doubleActionRate": 0
        },
        "raidTimeData": {
          "isActive": false,
          "gameLimit": 0,
          "clientLimit": 0,
          "commandLimit": 0,
          "pokeReviveTime": 0,
          "aiIntervalTime": 0,
          "aiIntervalRand": 0
        }
      }
    }
  ]
}
