{
  "values": [
    {
      "raidEnemyInfo": {
        "romVer": "BOTH",
        "no": 22001,
        "deliveryGroupID": 0,
        "difficulty": 0,
        "rate": 100,
        "dropTableFix": 4252614494071568324,
        "dropTableRandom": 18349317780833198619,
        "captureRate": 1,
        "captureLv": 20,
        "bossPokePara": {
          "devId": "DEV_MENOKURAGE",
          "formId": 0,
          "sex": "DEFAULT",
          "item": "ITEMID_NONE",
          "level": 20,
          "ballId": "NONE",
          "wazaType": "MANUAL",
          "waza1": {
            "wazaId": "WAZA_DOKUBARI",
            "pointUp": 0
          },
          "waza2": {
            "wazaId": "WAZA_MIZUDEPPOU",
            "pointUp": 0
          },
          "waza3": {
            "wazaId": "WAZA_YOUKAIEKI",
            "pointUp": 0
          },
          "waza4": {
            "wazaId": "WAZA_MIZUNOHADOU",
            "pointUp": 0
          },
          "gemType": "RANDOM",
          "seikaku": "DEFAULT",
          "tokusei": "RANDOM_12",
          "talentType": "V_NUM",
          "talentValue": {
            "hp": 0,
            "atk": 0,
            "def": 0,
            "spAtk": 0,
            "spDef": 0,
            "agi": 0
          },
          "talentVnum": 1,
          "effortValue": {
            "hp": 0,
            "atk": 0,
            "def": 0,
            "spAtk": 0,
            "spDef": 0,
            "agi": 0
          },
          "rareType": "DEFAULT",
          "scaleType": "RANDOM",
          "scaleValue": 0
        },
        "bossPokeSize": {
          "heightType": "RANDOM",
          "heigntValue": 0,
          "weightType": "RANDOM",
          "waightValue": 0,
          "scaleType": "RANDOM",
          "scaleValue": 0
        },
        "bossDesc": {
          "hpCoef": 500,
          "powerChargeTrigerHp": 0,
          "powerChargeTrigerTime": 0,
          "powerChargeLimitTime": 0,
          "powerChargeCancelDamage": 0,
          "powerChargePenaltyTime": 0,
          "powerChargePenaltyAction": "WAZA_NULL",
          "powerChargeDamageRate": 0,
          "powerChargeGemDamageRate": 0,
          "powerChargeChangeGemDamageRate": 0,
          "extraAction1": {
            "timming": "NONE",
            "action": "NONE",
            "value": 0,
            "wazano": "WAZA_NULL"
          },
          "extraAction2": {
            "timming": "NONE",
            "action": "NONE",
            "value": 0,
            "wazano": "WAZA_NULL"
          },
          "extraAction3": {
            "timming": "NONE",
            "action": "NONE",
            "value": 0,
            "wazano": "WAZA_NULL"
          },
          "extraAction4": {
            "timming": "NONE",
            "action": "NONE",
            "value": 0,
            "wazano": "WAZA_NULL"
          },
          "extraAction5": {
            "timming": "NONE",
            "action": "NONE",
            "value": 0,
            "wazano": "WAZA_NULL"
          },
          "extraAction6": {
            "timming": "NONE",
            "action": "NONE",
            "value": 0,
            "wazano": "WAZA_NULL"
          },
          "doubleActionTrigerHp": 0,
          "doubleActionTrigerTime": 0,
          "doubleActionRate": 0
        },
        "raidTimeData": {
          "isActive": false,
          "gameLimit": 0,
          "clientLimit": 0,
          "commandLimit": 0,
          "pokeReviveTime": 0,
          "aiIntervalTime": 0,
          "aiIntervalRand": 0
        }
      }
    },
    {
      "raidEnemyInfo": {
        "romVer": "BOTH",
        "no": 22002,
        "deliveryGroupID": 0,
        "difficulty": 0,
        "rate": 100,
        "dropTableFix": 13962751043364178541,
        "dropTableRandom": 6127935918080434284,
        "captureRate": 1,
        "captureLv": 20,
        "bossPokePara": {
          "devId": "DEV_DOODOO",
          "formId": 0,
          "sex": "DEFAULT",
          "item": "ITEMID_NONE",
          "level": 20,
          "ballId": "NONE",
          "wazaType": "MANUAL",
          "waza1": {
            "wazaId": "WAZA_TUTUKU",
            "pointUp": 0
          },
          "waza2": {
            "wazaId": "WAZA_TUIBAMU",
            "pointUp": 0
          },
          "waza3": {
            "wazaId": "WAZA_DAMEOSI",
            "pointUp": 0
          },
          "waza4": {
            "wazaId": "WAZA_NAKIGOE",
            "pointUp": 0
          },
          "gemType": "RANDOM",
          "seikaku": "DEFAULT",
          "tokusei": "RANDOM_12",
          "talentType": "V_NUM",
          "talentValue": {
            "hp": 0,
            "atk": 0,
            "def": 0,
            "spAtk": 0,
            "spDef": 0,
            "agi": 0
          },
          "talentVnum": 1,
          "effortValue": {
            "hp": 0,
            "atk": 0,
            "def": 0,
            "spAtk": 0,
            "spDef": 0,
            "agi": 0
          },
          "rareType": "DEFAULT",
          "scaleType": "RANDOM",
          "scaleValue": 0
        },
        "bossPokeSize": {
          "heightType": "RANDOM",
          "heigntValue": 0,
          "weightType": "RANDOM",
          "waightValue": 0,
          "scaleType": "RANDOM",
          "scaleValue": 0
        },
        "bossDesc": {
          "hpCoef": 500,
          "powerChargeTrigerHp": 0,
          "powerChargeTrigerTime": 0,
          "powerChargeLimitTime": 0,
          "powerChargeCancelDamage": 0,
          "powerChargePenaltyTime": 0,
          "powerChargePenaltyAction": "WAZA_NULL",
          "powerChargeDamageRate": 0,
          "powerChargeGemDamageRate": 0,
          "powerChargeChangeGemDamageRate": 0,
          "extraAction1": {
            "timming": "NONE",
            "action": "NONE",
            "value": 0,
            "wazano": "WAZA_NULL"
          },
          "extraAction2": {
            "timming": "NONE",
            "action": "NONE",
            "value": 0,
            "wazano": "WAZA_NULL"
          },
          "extraAction3": {
            "timming": "NONE",
            "action": "NONE",
            "value": 0,
            "wazano": "WAZA_NULL"
          },
          "extraAction4": {
            "timming": "NONE",
            "action": "NONE",
            "value": 0,
            "wazano": "WAZA_NULL"
          },
          "extraAction5": {
            "timming": "NONE",
            "action": "NONE",
            "value": 0,
            "wazano": "WAZA_NULL"
          },
          "extraAction6": {
            "timming": "NONE",
            "action": "NONE",
            "value": 0,
            "wazano": "WAZA_NULL"
          },
          "doubleActionTrigerHp": 0,
          "doubleActionTrigerTime": 0,
          "doubleActionRate": 0
        },
        "raidTimeData": {
          "isActive": false,
          "gameLimit": 0,
          "clientLimit": 0,
          "commandLimit": 0,
          "pokeReviveTime": 0,
          "aiIntervalTime": 0,
          "aiIntervalRand": 0
        }
      }
    },
    {
      "raidEnemyInfo": {
        "romVer": "BOTH",
        "no": 22003,
        "deliveryGroupID": 0,
        "difficulty": 0,
        "rate": 100,
        "dropTableFix": 4252614494071568324,
        "dropTableRandom": 18349317780833198619,
        "captureRate": 1,
        "captureLv": 20,
        "bossPokePara": {
          "devId": "DEV_PAUWAU",
          "formId": 0,
          "sex": "DEFAULT",
          "item": "ITEMID_NONE",
          "level": 20,
          "ballId": "NONE",
          "wazaType": "MANUAL",
          "waza1": {
            "wazaId": "WAZA_ZUTUKI",
            "pointUp": 0
          },
          "waza2": {
            "wazaId": "WAZA_KOGOERUKAZE",
            "pointUp": 0
          },
          "waza3": {
            "wazaId": "WAZA_AMAERU",
            "pointUp": 0
          },
          "waza4": {
            "wazaId": "WAZA_SITADENAMERU",
            "pointUp": 0
          },
          "gemType": "RANDOM",
          "seikaku": "DEFAULT",
          "tokusei": "RANDOM_12",
          "talentType": "V_NUM",
          "talentValue": {
            "hp": 0,
            "atk": 0,
            "def": 0,
            "spAtk": 0,
            "spDef": 0,
            "agi": 0
          },
          "talentVnum": 1,
          "effortValue": {
            "hp": 0,
            "atk": 0,
            "def": 0,
            "spAtk": 0,
            "spDef": 0,
            "agi": 0
          },
          "rareType": "DEFAULT",
          "scaleType": "RANDOM",
          "scaleValue": 0
        },
        "bossPokeSize": {
          "heightType": "RANDOM",
          "heigntValue": 0,
          "weightType": "RANDOM",
          "waightValue": 0,
          "scaleType": "RANDOM",
          "scaleValue": 0
        },
        "bossDesc": {
          "hpCoef": 500,
          "powerChargeTrigerHp": 0,
          "powerChargeTrigerTime": 0,
          "powerChargeLimitTime": 0,
          "powerChargeCancelDamage": 0,
          "powerChargePenaltyTime": 0,
          "powerChargePenaltyAction": "WAZA_NULL",
          "powerChargeDamageRate": 0,
          "powerChargeGemDamageRate": 0,
          "powerChargeChangeGemDamageRate": 0,
          "extraAction1": {
            "timming": "NONE",
            "action": "NONE",
            "value": 0,
            "wazano": "WAZA_NULL"
          },
          "extraAction2": {
            "timming": "NONE",
            "action": "NONE",
            "value": 0,
            "wazano": "WAZA_NULL"
          },
          "extraAction3": {
            "timming": "NONE",
            "action": "NONE",
            "value": 0,
            "wazano": "WAZA_NULL"
          },
          "extraAction4": {
            "timming": "NONE",
            "action": "NONE",
            "value": 0,
            "wazano": "WAZA_NULL"
          },
          "extraAction5": {
            "timming": "NONE",
            "action": "NONE",
            "value": 0,
            "wazano": "WAZA_NULL"
          },
          "extraAction6": {
            "timming": "NONE",
            "action": "NONE",
            "value": 0,
            "wazano": "WAZA_NULL"
          },
          "doubleActionTrigerHp": 0,
          "doubleActionTrigerTime": 0,
          "doubleActionRate": 0
        },
        "raidTimeData": {
          "isActive": false,
          "gameLimit": 0,
          "clientLimit": 0,
          "commandLimit": 0,
          "pokeReviveTime": 0,
          "aiIntervalTime": 0,
          "aiIntervalRand": 0
        }
      }
    },
    {
      "raidEnemyInfo": {
        "romVer": "BOTH",
        "no": 22004,
        "deliveryGroupID": 0,
        "difficulty": 0,
        "rate": 100,
        "dropTableFix": 18330603432922962524,
        "dropTableRandom": 15677658920486028021,
        "captureRate": 1,
        "captureLv": 20,
        "bossPokePara": {
          "devId": "DEV_EREKIDDO",
          "formId": 0,
          "sex": "DEFAULT",
          "item": "ITEMID_NONE",
          "level": 20,
          "ballId": "NONE",
          "wazaType": "MANUAL",
          "waza1": {
            "wazaId": "WAZA_DENKISYOKKU",
            "pointUp": 0
          },
          "waza2": {
            "wazaId": "WAZA_NIRAMITUKERU",
            "pointUp": 0
          },
          "waza3": {
            "wazaId": "WAZA_DENKOUSEKKA",
            "pointUp": 0
          },
          "waza4": {
            "wazaId": "WAZA_DENGEKIHA",
            "pointUp": 0
          },
          "gemType": "RANDOM",
          "seikaku": "DEFAULT",
          "tokusei": "RANDOM_12",
          "talentType": "V_NUM",
          "talentValue": {
            "hp": 0,
            "atk": 0,
            "def": 0,
            "spAtk": 0,
            "spDef": 0,
            "agi": 0
          },
          "talentVnum": 1,
          "effortValue": {
            "hp": 0,
            "atk": 0,
            "def": 0,
            "spAtk": 0,
            "spDef": 0,
            "agi": 0
          },
          "rareType": "DEFAULT",
          "scaleType": "RANDOM",
          "scaleValue": 0
        },
        "bossPokeSize": {
          "heightType": "RANDOM",
          "heigntValue": 0,
          "weightType": "RANDOM",
          "waightValue": 0,
          "scaleType": "RANDOM",
          "scaleValue": 0
        },
        "bossDesc": {
          "hpCoef": 500,
          "powerChargeTrigerHp": 0,
          "powerChargeTrigerTime": 0,
          "powerChargeLimitTime": 0,
          "powerChargeCancelDamage": 0,
          "powerChargePenaltyTime": 0,
          "powerChargePenaltyAction": "WAZA_NULL",
          "powerChargeDamageRate": 0,
          "powerChargeGemDamageRate": 0,
          "powerChargeChangeGemDamageRate": 0,
          "extraAction1": {
            "timming": "NONE",
            "action": "NONE",
            "value": 0,
            "wazano": "WAZA_NULL"
          },
          "extraAction2": {
            "timming": "NONE",
            "action": "NONE",
            "value": 0,
            "wazano": "WAZA_NULL"
          },
          "extraAction3": {
            "timming": "NONE",
            "action": "NONE",
            "value": 0,
            "wazano": "WAZA_NULL"
          },
          "extraAction4": {
            "timming": "NONE",
            "action": "NONE",
            "value": 0,
            "wazano": "WAZA_NULL"
          },
          "extraAction5": {
            "timming": "NONE",
            "action": "NONE",
            "value": 0,
            "wazano": "WAZA_NULL"
          },
          "extraAction6": {
            "timming": "NONE",
            "action": "NONE",
            "value": 0,
            "wazano": "WAZA_NULL"
          },
          "doubleActionTrigerHp": 0,
          "doubleActionTrigerTime": 0,
          "doubleActionRate": 0
        },
        "raidTimeData": {
          "isActive": false,
          "gameLimit": 0,
          "clientLimit": 0,
          "commandLimit": 0,
          "pokeReviveTime": 0,
          "aiIntervalTime": 0,
          "aiIntervalRand": 0
        }
      }
    },
    {
      "raidEnemyInfo": {
        "romVer": "BOTH",
        "no": 22005,
        "deliveryGroupID": 0,
        "difficulty": 0,
        "rate": 100,
        "dropTableFix": 13962751043364178541,
        "dropTableRandom": 6127935918080434284,
        "captureRate": 1,
        "captureLv": 20,
        "bossPokePara": {
          "devId": "DEV_BUBHI",
          "formId": 0,
          "sex": "DEFAULT",
          "item": "ITEMID_NONE",
          "level": 20,
          "ballId": "NONE",
          "wazaType": "MANUAL",
          "waza1": {
            "wazaId": "WAZA_HINOKO",
            "pointUp": 0
          },
          "waza2": {
            "wazaId": "WAZA_SUMOGGU",
            "pointUp": 0
          },
          "waza3": {
            "wazaId": "WAZA_KAENGURUMA",
            "pointUp": 0
          },
          "waza4": {
            "wazaId": "WAZA_NIRAMITUKERU",
            "pointUp": 0
          },
          "gemType": "RANDOM",
          "seikaku": "DEFAULT",
          "tokusei": "RANDOM_12",
          "talentType": "V_NUM",
          "talentValue": {
            "hp": 0,
            "atk": 0,
            "def": 0,
            "spAtk": 0,
            "spDef": 0,
            "agi": 0
          },
          "talentVnum": 1,
          "effortValue": {
            "hp": 0,
            "atk": 0,
            "def": 0,
            "spAtk": 0,
            "spDef": 0,
            "agi": 0
          },
          "rareType": "DEFAULT",
          "scaleType": "RANDOM",
          "scaleValue": 0
        },
        "bossPokeSize": {
          "heightType": "RANDOM",
          "heigntValue": 0,
          "weightType": "RANDOM",
          "waightValue": 0,
          "scaleType": "RANDOM",
          "scaleValue": 0
        },
        "bossDesc": {
          "hpCoef": 500,
          "powerChargeTrigerHp": 0,
          "powerChargeTrigerTime": 0,
          "powerChargeLimitTime": 0,
          "powerChargeCancelDamage": 0,
          "powerChargePenaltyTime": 0,
          "powerChargePenaltyAction": "WAZA_NULL",
          "powerChargeDamageRate": 0,
          "powerChargeGemDamageRate": 0,
          "powerChargeChangeGemDamageRate": 0,
          "extraAction1": {
            "timming": "NONE",
            "action": "NONE",
            "value": 0,
            "wazano": "WAZA_NULL"
          },
          "extraAction2": {
            "timming": "NONE",
            "action": "NONE",
            "value": 0,
            "wazano": "WAZA_NULL"
          },
          "extraAction3": {
            "timming": "NONE",
            "action": "NONE",
            "value": 0,
            "wazano": "WAZA_NULL"
          },
          "extraAction4": {
            "timming": "NONE",
            "action": "NONE",
            "value": 0,
            "wazano": "WAZA_NULL"
          },
          "extraAction5": {
            "timming": "NONE",
            "action": "NONE",
            "value": 0,
            "wazano": "WAZA_NULL"
          },
          "extraAction6": {
            "timming": "NONE",
            "action": "NONE",
            "value": 0,
            "wazano": "WAZA_NULL"
          },
          "doubleActionTrigerHp": 0,
          "doubleActionTrigerTime": 0,
          "doubleActionRate": 0
        },
        "raidTimeData": {
          "isActive": false,
          "gameLimit": 0,
          "clientLimit": 0,
          "commandLimit": 0,
          "pokeReviveTime": 0,
          "aiIntervalTime": 0,
          "aiIntervalRand": 0
        }
      }
    },
    {
      "raidEnemyInfo": {
        "romVer": "BOTH",
        "no": 22006,
        "deliveryGroupID": 0,
        "difficulty": 0,
        "rate": 100,
        "dropTableFix": 13962751043364178541,
        "dropTableRandom": 6127935918080434284,
        "captureRate": 1,
        "captureLv": 20,
        "bossPokePara": {
          "devId": "DEV_NAKKURAA",
          "formId": 0,
          "sex": "DEFAULT",
          "item": "ITEMID_NONE",
          "level": 20,
          "ballId": "NONE",
          "wazaType": "MANUAL",
          "waza1": {
            "wazaId": "WAZA_KAMITUKU",
            "pointUp": 0
          },
          "waza2": {
            "wazaId": "WAZA_DOROKAKE",
            "pointUp": 0
          },
          "waza3": {
            "wazaId": "WAZA_SUNAKAKE",
            "pointUp": 0
          },
          "waza4": {
            "wazaId": "WAZA_ODOROKASU",
            "pointUp": 0
          },
          "gemType": "RANDOM",
          "seikaku": "DEFAULT",
          "tokusei": "RANDOM_12",
          "talentType": "V_NUM",
          "talentValue": {
            "hp": 0,
            "atk": 0,
            "def": 0,
            "spAtk": 0,
            "spDef": 0,
            "agi": 0
          },
          "talentVnum": 1,
          "effortValue": {
            "hp": 0,
            "atk": 0,
            "def": 0,
            "spAtk": 0,
            "spDef": 0,
            "agi": 0
          },
          "rareType": "DEFAULT",
          "scaleType": "RANDOM",
          "scaleValue": 0
        },
        "bossPokeSize": {
          "heightType": "RANDOM",
          "heigntValue": 0,
          "weightType": "RANDOM",
          "waightValue": 0,
          "scaleType": "RANDOM",
          "scaleValue": 0
        },
        "bossDesc": {
          "hpCoef": 500,
          "powerChargeTrigerHp": 0,
          "powerChargeTrigerTime": 0,
          "powerChargeLimitTime": 0,
          "powerChargeCancelDamage": 0,
          "powerChargePenaltyTime": 0,
          "powerChargePenaltyAction": "WAZA_NULL",
          "powerChargeDamageRate": 0,
          "powerChargeGemDamageRate": 0,
          "powerChargeChangeGemDamageRate": 0,
          "extraAction1": {
            "timming": "NONE",
            "action": "NONE",
            "value": 0,
            "wazano": "WAZA_NULL"
          },
          "extraAction2": {
            "timming": "NONE",
            "action": "NONE",
            "value": 0,
            "wazano": "WAZA_NULL"
          },
          "extraAction3": {
            "timming": "NONE",
            "action": "NONE",
            "value": 0,
            "wazano": "WAZA_NULL"
          },
          "extraAction4": {
            "timming": "NONE",
            "action": "NONE",
            "value": 0,
            "wazano": "WAZA_NULL"
          },
          "extraAction5": {
            "timming": "NONE",
            "action": "NONE",
            "value": 0,
            "wazano": "WAZA_NULL"
          },
          "extraAction6": {
            "timming": "NONE",
            "action": "NONE",
            "value": 0,
            "wazano": "WAZA_NULL"
          },
          "doubleActionTrigerHp": 0,
          "doubleActionTrigerTime": 0,
          "doubleActionRate": 0
        },
        "raidTimeData": {
          "isActive": false,
          "gameLimit": 0,
          "clientLimit": 0,
          "commandLimit": 0,
          "pokeReviveTime": 0,
          "aiIntervalTime": 0,
          "aiIntervalRand": 0
        }
      }
    },
    {
      "raidEnemyInfo": {
        "romVer": "BOTH",
        "no": 22007,
        "deliveryGroupID": 0,
        "difficulty": 0,
        "rate": 100,
        "dropTableFix": 2509815283604296356,
        "dropTableRandom": 18274910994316513853,
        "captureRate": 1,
        "captureLv": 20,
        "bossPokePara": {
          "devId": "DEV_MONMEN",
          "formId": 0,
          "sex": "DEFAULT",
          "item": "ITEMID_NONE",
          "level": 20,
          "ballId": "NONE",
          "wazaType": "MANUAL",
          "waza1": {
            "wazaId": "WAZA_YOUSEINOKAZE",
            "pointUp": 0
          },
          "waza2": {
            "wazaId": "WAZA_SIBIREGONA",
            "pointUp": 0
          },
          "waza3": {
            "wazaId": "WAZA_HAPPAKATTAA",
            "pointUp": 0
          },
          "waza4": {
            "wazaId": "WAZA_SEITYOU",
            "pointUp": 0
          },
          "gemType": "RANDOM",
          "seikaku": "DEFAULT",
          "tokusei": "RANDOM_12",
          "talentType": "V_NUM",
          "talentValue": {
            "hp": 0,
            "atk": 0,
            "def": 0,
            "spAtk": 0,
            "spDef": 0,
            "agi": 0
          },
          "talentVnum": 1,
          "effortValue": {
            "hp": 0,
            "atk": 0,
            "def": 0,
            "spAtk": 0,
            "spDef": 0,
            "agi": 0
          },
          "rareType": "DEFAULT",
          "scaleType": "RANDOM",
          "scaleValue": 0
        },
        "bossPokeSize": {
          "heightType": "RANDOM",
          "heigntValue": 0,
          "weightType": "RANDOM",
          "waightValue": 0,
          "scaleType": "RANDOM",
          "scaleValue": 0
        },
        "bossDesc": {
          "hpCoef": 500,
          "powerChargeTrigerHp": 0,
          "powerChargeTrigerTime": 0,
          "powerChargeLimitTime": 0,
          "powerChargeCancelDamage": 0,
          "powerChargePenaltyTime": 0,
          "powerChargePenaltyAction": "WAZA_NULL",
          "powerChargeDamageRate": 0,
          "powerChargeGemDamageRate": 0,
          "powerChargeChangeGemDamageRate": 0,
          "extraAction1": {
            "timming": "NONE",
            "action": "NONE",
            "value": 0,
            "wazano": "WAZA_NULL"
          },
          "extraAction2": {
            "timming": "NONE",
            "action": "NONE",
            "value": 0,
            "wazano": "WAZA_NULL"
          },
          "extraAction3": {
            "timming": "NONE",
            "action": "NONE",
            "value": 0,
            "wazano": "WAZA_NULL"
          },
          "extraAction4": {
            "timming": "NONE",
            "action": "NONE",
            "value": 0,
            "wazano": "WAZA_NULL"
          },
          "extraAction5": {
            "timming": "NONE",
            "action": "NONE",
            "value": 0,
            "wazano": "WAZA_NULL"
          },
          "extraAction6": {
            "timming": "NONE",
            "action": "NONE",
            "value": 0,
            "wazano": "WAZA_NULL"
          },
          "doubleActionTrigerHp": 0,
          "doubleActionTrigerTime": 0,
          "doubleActionRate": 0
        },
        "raidTimeData": {
          "isActive": false,
          "gameLimit": 0,
          "clientLimit": 0,
          "commandLimit": 0,
          "pokeReviveTime": 0,
          "aiIntervalTime": 0,
          "aiIntervalRand": 0
        }
      }
    },
    {
      "raidEnemyInfo": {
        "romVer": "BOTH",
        "no": 22008,
        "deliveryGroupID": 0,
        "difficulty": 0,
        "rate": 100,
        "dropTableFix": 2509815283604296356,
        "dropTableRandom": 18274910994316513853,
        "captureRate": 1,
        "captureLv": 20,
        "bossPokePara": {
          "devId": "DEV_TIRAAMHI",
          "formId": 0,
          "sex": "DEFAULT",
          "item": "ITEMID_NONE",
          "level": 20,
          "ballId": "NONE",
          "wazaType": "MANUAL",
          "waza1": {
            "wazaId": "WAZA_HATAKU",
            "pointUp": 0
          },
          "waza2": {
            "wazaId": "WAZA_TUBURANAHITOMI",
            "pointUp": 0
          },
          "waza3": {
            "wazaId": "WAZA_SIPPOWOHURU",
            "pointUp": 0
          },
          "waza4": {
            "wazaId": "WAZA_TANEMASINGAN",
            "pointUp": 0
          },
          "gemType": "RANDOM",
          "seikaku": "DEFAULT",
          "tokusei": "RANDOM_12",
          "talentType": "V_NUM",
          "talentValue": {
            "hp": 0,
            "atk": 0,
            "def": 0,
            "spAtk": 0,
            "spDef": 0,
            "agi": 0
          },
          "talentVnum": 1,
          "effortValue": {
            "hp": 0,
            "atk": 0,
            "def": 0,
            "spAtk": 0,
            "spDef": 0,
            "agi": 0
          },
          "rareType": "DEFAULT",
          "scaleType": "RANDOM",
          "scaleValue": 0
        },
        "bossPokeSize": {
          "heightType": "RANDOM",
          "heigntValue": 0,
          "weightType": "RANDOM",
          "waightValue": 0,
          "scaleType": "RANDOM",
          "scaleValue": 0
        },
        "bossDesc": {
          "hpCoef": 500,
          "powerChargeTrigerHp": 0,
          "powerChargeTrigerTime": 0,
          "powerChargeLimitTime": 0,
          "powerChargeCancelDamage": 0,
          "powerChargePenaltyTime": 0,
          "powerChargePenaltyAction": "WAZA_NULL",
          "powerChargeDamageRate": 0,
          "powerChargeGemDamageRate": 0,
          "powerChargeChangeGemDamageRate": 0,
          "extraAction1": {
            "timming": "NONE",
            "action": "NONE",
            "value": 0,
            "wazano": "WAZA_NULL"
          },
          "extraAction2": {
            "timming": "NONE",
            "action": "NONE",
            "value": 0,
            "wazano": "WAZA_NULL"
          },
          "extraAction3": {
            "timming": "NONE",
            "action": "NONE",
            "value": 0,
            "wazano": "WAZA_NULL"
          },
          "extraAction4": {
            "timming": "NONE",
            "action": "NONE",
            "value": 0,
            "wazano": "WAZA_NULL"
          },
          "extraAction5": {
            "timming": "NONE",
            "action": "NONE",
            "value": 0,
            "wazano": "WAZA_NULL"
          },
          "extraAction6": {
            "timming": "NONE",
            "action": "NONE",
            "value": 0,
            "wazano": "WAZA_NULL"
          },
          "doubleActionTrigerHp": 0,
          "doubleActionTrigerTime": 0,
          "doubleActionRate": 0
        },
        "raidTimeData": {
          "isActive": false,
          "gameLimit": 0,
          "clientLimit": 0,
          "commandLimit": 0,
          "pokeReviveTime": 0,
          "aiIntervalTime": 0,
          "aiIntervalRand": 0
        }
      }
    },
    {
      "raidEnemyInfo": {
        "romVer": "BOTH",
        "no": 22009,
        "deliveryGroupID": 0,
        "difficulty": 0,
        "rate": 100,
        "dropTableFix": 18330603432922962524,
        "dropTableRandom": 15677658920486028021,
        "captureRate": 1,
        "captureLv": 20,
        "bossPokePara": {
          "devId": "DEV_YUNIRAN",
          "formId": 0,
          "sex": "DEFAULT",
          "item": "ITEMID_NONE",
          "level": 20,
          "ballId": "NONE",
          "wazaType": "MANUAL",
          "waza1": {
            "wazaId": "WAZA_NENRIKI",
            "pointUp": 0
          },
          "waza2": {
            "wazaId": "WAZA_AYASIIHIKARI",
            "pointUp": 0
          },
          "waza3": {
            "wazaId": "WAZA_ODOROKASU",
            "pointUp": 0
          },
          "waza4": {
            "wazaId": "WAZA_SUPIIDOSUTAA",
            "pointUp": 0
          },
          "gemType": "RANDOM",
          "seikaku": "DEFAULT",
          "tokusei": "RANDOM_12",
          "talentType": "V_NUM",
          "talentValue": {
            "hp": 0,
            "atk": 0,
            "def": 0,
            "spAtk": 0,
            "spDef": 0,
            "agi": 0
          },
          "talentVnum": 1,
          "effortValue": {
            "hp": 0,
            "atk": 0,
            "def": 0,
            "spAtk": 0,
            "spDef": 0,
            "agi": 0
          },
          "rareType": "DEFAULT",
          "scaleType": "RANDOM",
          "scaleValue": 0
        },
        "bossPokeSize": {
          "heightType": "RANDOM",
          "heigntValue": 0,
          "weightType": "RANDOM",
          "waightValue": 0,
          "scaleType": "RANDOM",
          "scaleValue": 0
        },
        "bossDesc": {
          "hpCoef": 500,
          "powerChargeTrigerHp": 0,
          "powerChargeTrigerTime": 0,
          "powerChargeLimitTime": 0,
          "powerChargeCancelDamage": 0,
          "powerChargePenaltyTime": 0,
          "powerChargePenaltyAction": "WAZA_NULL",
          "powerChargeDamageRate": 0,
          "powerChargeGemDamageRate": 0,
          "powerChargeChangeGemDamageRate": 0,
          "extraAction1": {
            "timming": "NONE",
            "action": "NONE",
            "value": 0,
            "wazano": "WAZA_NULL"
          },
          "extraAction2": {
            "timming": "NONE",
            "action": "NONE",
            "value": 0,
            "wazano": "WAZA_NULL"
          },
          "extraAction3": {
            "timming": "NONE",
            "action": "NONE",
            "value": 0,
            "wazano": "WAZA_NULL"
          },
          "extraAction4": {
            "timming": "NONE",
            "action": "NONE",
            "value": 0,
            "wazano": "WAZA_NULL"
          },
          "extraAction5": {
            "timming": "NONE",
            "action": "NONE",
            "value": 0,
            "wazano": "WAZA_NULL"
          },
          "extraAction6": {
            "timming": "NONE",
            "action": "NONE",
            "value": 0,
            "wazano": "WAZA_NULL"
          },
          "doubleActionTrigerHp": 0,
          "doubleActionTrigerTime": 0,
          "doubleActionRate": 0
        },
        "raidTimeData": {
          "isActive": false,
          "gameLimit": 0,
          "clientLimit": 0,
          "commandLimit": 0,
          "pokeReviveTime": 0,
          "aiIntervalTime": 0,
          "aiIntervalRand": 0
        }
      }
    },
    {
      "raidEnemyInfo": {
        "romVer": "BOTH",
        "no": 22010,
        "deliveryGroupID": 0,
        "difficulty": 0,
        "rate": 100,
        "dropTableFix": 7425207459411916467,
        "dropTableRandom": 875344009101998740,
        "captureRate": 1,
        "captureLv": 20,
        "bossPokePara": {
          "devId": "DEV_SIZUKUMO",
          "formId": 0,
          "sex": "DEFAULT",
          "item": "ITEMID_NONE",
          "level": 20,
          "ballId": "NONE",
          "wazaType": "MANUAL",
          "waza1": {
            "wazaId": "WAZA_MIZUDEPPOU",
            "pointUp": 0
          },
          "waza2": {
            "wazaId": "WAZA_MUSIKUI",
            "pointUp": 0
          },
          "waza3": {
            "wazaId": "WAZA_KAMITUKU",
            "pointUp": 0
          },
          "waza4": {
            "wazaId": "WAZA_BABURUKOUSEN",
            "pointUp": 0
          },
          "gemType": "RANDOM",
          "seikaku": "DEFAULT",
          "tokusei": "RANDOM_12",
          "talentType": "V_NUM",
          "talentValue": {
            "hp": 0,
            "atk": 0,
            "def": 0,
            "spAtk": 0,
            "spDef": 0,
            "agi": 0
          },
          "talentVnum": 1,
          "effortValue": {
            "hp": 0,
            "atk": 0,
            "def": 0,
            "spAtk": 0,
            "spDef": 0,
            "agi": 0
          },
          "rareType": "DEFAULT",
          "scaleType": "RANDOM",
          "scaleValue": 0
        },
        "bossPokeSize": {
          "heightType": "RANDOM",
          "heigntValue": 0,
          "weightType": "RANDOM",
          "waightValue": 0,
          "scaleType": "RANDOM",
          "scaleValue": 0
        },
        "bossDesc": {
          "hpCoef": 500,
          "powerChargeTrigerHp": 0,
          "powerChargeTrigerTime": 0,
          "powerChargeLimitTime": 0,
          "powerChargeCancelDamage": 0,
          "powerChargePenaltyTime": 0,
          "powerChargePenaltyAction": "WAZA_NULL",
          "powerChargeDamageRate": 0,
          "powerChargeGemDamageRate": 0,
          "powerChargeChangeGemDamageRate": 0,
          "extraAction1": {
            "timming": "NONE",
            "action": "NONE",
            "value": 0,
            "wazano": "WAZA_NULL"
          },
          "extraAction2": {
            "timming": "NONE",
            "action": "NONE",
            "value": 0,
            "wazano": "WAZA_NULL"
          },
          "extraAction3": {
            "timming": "NONE",
            "action": "NONE",
            "value": 0,
            "wazano": "WAZA_NULL"
          },
          "extraAction4": {
            "timming": "NONE",
            "action": "NONE",
            "value": 0,
            "wazano": "WAZA_NULL"
          },
          "extraAction5": {
            "timming": "NONE",
            "action": "NONE",
            "value": 0,
            "wazano": "WAZA_NULL"
          },
          "extraAction6": {
            "timming": "NONE",
            "action": "NONE",
            "value": 0,
            "wazano": "WAZA_NULL"
          },
          "doubleActionTrigerHp": 0,
          "doubleActionTrigerTime": 0,
          "doubleActionRate": 0
        },
        "raidTimeData": {
          "isActive": false,
          "gameLimit": 0,
          "clientLimit": 0,
          "commandLimit": 0,
          "pokeReviveTime": 0,
          "aiIntervalTime": 0,
          "aiIntervalRand": 0
        }
      }
    },
    {
      "raidEnemyInfo": {
        "romVer": "BOTH",
        "no": 22011,
        "deliveryGroupID": 0,
        "difficulty": 0,
        "rate": 100,
        "dropTableFix": 7425207459411916467,
        "dropTableRandom": 875344009101998740,
        "captureRate": 1,
        "captureLv": 20,
        "bossPokePara": {
          "devId": "DEV_MAHOMIRU",
          "formId": 0,
          "sex": "DEFAULT",
          "item": "ITEMID_NONE",
          "level": 20,
          "ballId": "NONE",
          "wazaType": "MANUAL",
          "waza1": {
            "wazaId": "WAZA_TAIATARI",
            "pointUp": 0
          },
          "waza2": {
            "wazaId": "WAZA_AMAIKAORI",
            "pointUp": 0
          },
          "waza3": {
            "wazaId": "WAZA_ASISUTOPAWAA",
            "pointUp": 0
          },
          "waza4": {
            "wazaId": "WAZA_DOREINKISSU",
            "pointUp": 0
          },
          "gemType": "RANDOM",
          "seikaku": "DEFAULT",
          "tokusei": "RANDOM_12",
          "talentType": "V_NUM",
          "talentValue": {
            "hp": 0,
            "atk": 0,
            "def": 0,
            "spAtk": 0,
            "spDef": 0,
            "agi": 0
          },
          "talentVnum": 1,
          "effortValue": {
            "hp": 0,
            "atk": 0,
            "def": 0,
            "spAtk": 0,
            "spDef": 0,
            "agi": 0
          },
          "rareType": "DEFAULT",
          "scaleType": "RANDOM",
          "scaleValue": 0
        },
        "bossPokeSize": {
          "heightType": "RANDOM",
          "heigntValue": 0,
          "weightType": "RANDOM",
          "waightValue": 0,
          "scaleType": "RANDOM",
          "scaleValue": 0
        },
        "bossDesc": {
          "hpCoef": 500,
          "powerChargeTrigerHp": 0,
          "powerChargeTrigerTime": 0,
          "powerChargeLimitTime": 0,
          "powerChargeCancelDamage": 0,
          "powerChargePenaltyTime": 0,
          "powerChargePenaltyAction": "WAZA_NULL",
          "powerChargeDamageRate": 0,
          "powerChargeGemDamageRate": 0,
          "powerChargeChangeGemDamageRate": 0,
          "extraAction1": {
            "timming": "NONE",
            "action": "NONE",
            "value": 0,
            "wazano": "WAZA_NULL"
          },
          "extraAction2": {
            "timming": "NONE",
            "action": "NONE",
            "value": 0,
            "wazano": "WAZA_NULL"
          },
          "extraAction3": {
            "timming": "NONE",
            "action": "NONE",
            "value": 0,
            "wazano": "WAZA_NULL"
          },
          "extraAction4": {
            "timming": "NONE",
            "action": "NONE",
            "value": 0,
            "wazano": "WAZA_NULL"
          },
          "extraAction5": {
            "timming": "NONE",
            "action": "NONE",
            "value": 0,
            "wazano": "WAZA_NULL"
          },
          "extraAction6": {
            "timming": "NONE",
            "action": "NONE",
            "value": 0,
            "wazano": "WAZA_NULL"
          },
          "doubleActionTrigerHp": 0,
          "doubleActionTrigerTime": 0,
          "doubleActionRate": 0
        },
        "raidTimeData": {
          "isActive": false,
          "gameLimit": 0,
          "clientLimit": 0,
          "commandLimit": 0,
          "pokeReviveTime": 0,
          "aiIntervalTime": 0,
          "aiIntervalRand": 0
        }
      }
    }
  ]
}
